Workbook
Name ROI_период: Дашборд!$K$6
Name Банк_комиссия: Допущения!$C$11
Name Возврат_логистика: Допущения!$C$17
Name Выручка_итого: Дашборд!$B$6
Name Выручка_макс_год: ОПиУ!$D$55
Name Дата_начала: Допущения!$C$7
Name Деньги_конец: 'Денежный поток'!$D$75
Name Дней_в_месяце: Допущения!$C$24
Name Доставка_до_МП: Допущения!$C$16
Name Доставка_кг: Допущения!$C$13
Name Доставка_м3: Допущения!$C$14
Name Доставка_номер: Сценарии!$C$20
Name Доставка_список: Допущения!$A$76:$A$78
Name Доставка_способ: Допущения!$C$12
Name ДРР: Сценарии!$C$18
Name ДРР_база: Допущения!$C$18
Name Задержка_выплат_дн: Допущения!$C$23
Name Капитал_конец: Дашборд!$K$10
Name Капитал_старт: Допущения!$C$8
Name Комиссия_агента: Допущения!$C$10
Name Контроль_баланса: 'Денежный поток'!$D$84
Name Курс: Сценарии!$C$15
Name Курс_анализ: Чувствительность!$C$6
Name Курс_база: Допущения!$C$9
Name Лимит_НПД: Допущения!$C$33
Name Макс_разрыв: Дашборд!$E$10
Name Мин_налог_УСН15: Допущения!$C$32
Name Множитель_продаж: Сценарии!$C$17
Name Множитель_цены: Сценарии!$C$16
Name Налог_номер: Сценарии!$C$19
Name Налог_режим: Допущения!$C$27
Name Налог_список: Допущения!$A$29:$A$31
Name Объём_анализ: Чувствительность!$C$8
Name Окупаемость_мес: Дашборд!$H$10
Name Первый_разрыв: Дашборд!$E$11
Name Пик_вложений: Дашборд!$B$10
Name Порог_НДС_УСН: Допущения!$C$34
Name Пост_расходы: Допущения!$C$19
Name Рентабельность: Дашборд!$H$6
Name Срок_поставки: Допущения!$C$21
Name Ставка_НПД: Допущения!$C$31
Name Ставка_УСН15: Допущения!$C$30
Name Ставка_УСН6: Допущения!$C$29
Name Старт_расходы: Допущения!$C$20
Name Страх_запас: Допущения!$C$22
Name Сценарий_выбор: Сценарии!$C$5
Name Сценарий_номер: Сценарии!$C$21
Name Сценарий_ручной: Сценарии!$C$22
Name Тамож_оформление: Допущения!$C$15
Name Темп_продаж: Допущения!$C$56:$C$73
Name Упущено_шт: 'Закупки и склад'!$D$37
Name Цена_анализ: Чувствительность!$C$7
Name ЧП_итого: Дашборд!$E$6

Sheet Инструкция
B1: Финансовая модель: импорт автотоваров из Китая и продажа на маркетплейсах
B2: ДЕМО-ДАННЫЕ: все цифры — пример. Ставки пошлин, НДС, налогов и тарифы маркетплейса уточните под свой товар.
B4: Что считает модель
C5: • Закупку товара в Китае партиями, доставку, таможенные платежи и продажи на маркетплейсе на 18 месяцев вперёд.
C6: • Юнит-экономику каждого товара: полную себестоимость, прибыль, маржу, наценку, ROI и точку безубыточности.
C7: • Денежный поток: когда уходят деньги на закупку и когда приходят выплаты маркетплейса; показывает кассовый разрыв — месяцы, когда денег не хватает.
C8: • ОПиУ (прибыль и убытки) по месяцам с налогом по выбранному режиму.
C9: • Три сценария (базовый, пессимистичный, оптимистичный) и таблицы чувствительности к курсу юаня, цене и объёму продаж.
B11: Как пользоваться
B12: 1. Допущения | C12: Впишите свои данные в жёлтые ячейки: курс, тарифы доставки, товары (закупка в юанях, вес, объём, партия, цена продажи, плато продаж), ставки пошлины и НДС, комиссию и логистику маркетплейса, налоговый режим, стартовый капитал.
B13: 2. Темп продаж | C13: На листе «Допущения», раздел 4: сколько процентов от плато продаётся в каждом месяце. Первые месяцы товар едет — ставьте 0 %.
B14: 3. Сценарии | C14: Выберите сценарий в жёлтой ячейке листа «Сценарии». Проценты отклонений тоже можно менять.
B15: 4. Дашборд | C15: Главные цифры, предупреждения и графики. Красное — внимание: кассовый разрыв, убыточный товар.
B16: 5. Детали | C16: «Юнит-экономика» — каждая статья затрат на 1 шт; «Закупки и склад» — когда и сколько заказывать; «Денежный поток» и «ОПиУ» — по месяцам.
B17: 6. Чувствительность | C17: Сколько заработаете при другом курсе, цене или объёме — без ручного перебора.
B19: Цвета ячеек
B20: Ввод данных | C20: Жёлтая ячейка с синим шрифтом — меняйте. Только эти ячейки не защищены.
B21: Расчёт | C21: Белая ячейка — формула. Защищена от случайной правки.
B22: Итог | C22: Серая ячейка с жирным шрифтом — итоговая строка.
B23: Служебная | C23: Серый курсив — техническая ячейка модели, не меняйте.
B24: Внимание | C24: Красная заливка — кассовый разрыв, убыток, нехватка товара.
B25: Заказ | C25: Зелёная заливка на листе «Закупки и склад» — месяц заказа партии.
B27: Листы книги (нажмите, чтобы перейти)
B28: Дашборд | C28: главные показатели, предупреждения, графики; печатается на одну страницу
B29: Допущения | C29: все исходные данные — только здесь и на листе «Сценарии»
B30: Сценарии | C30: выбор сценария и сравнение трёх сценариев в одной таблице
B31: Юнит-экономика | C31: расчёт на 1 проданную единицу по каждому товару
B32: Закупки и склад | C32: спрос, продажи, остатки, товар в пути, заказы партиями
B33: Денежный поток | C33: поступления и выплаты по месяцам, остаток денег, кассовый разрыв, контроль баланса
B34: ОПиУ | C34: выручка, себестоимость, расходы, налог, чистая прибыль по месяцам
B35: Чувствительность | C35: таблицы «что если»: курс × цена, курс × объём
B37: Допущения и упрощения
C38: • Курс юаня постоянный внутри сценария; колебания курса — через сценарии и лист «Чувствительность».
C39: • Таможенная стоимость = товар + доставка до склада в РФ (консервативно). Пошлина — от таможенной стоимости, НДС на ввоз — от таможенной стоимости с пошлиной. НДС на ввоз включён в себестоимость: на УСН и НПД он к вычету не принимается.
C40: • Ставки пошлин, НДС, налогов, тарифы доставки и маркетплейса в книге — ПРИМЕР. Задайте свои: пошлина — по коду ТН ВЭД, комиссия — по категории товара на своей площадке.
C41: • Продажи = выкупы. Возвраты увеличивают логистику маркетплейса (доставка туда и обратно), возвращённый товар снова идёт в продажу.
C42: • Заказ поставщику: товар оплачивается в месяц заказа, доставка и таможня — в месяц поступления. Заказ кратен партии; продажи не превышают остаток на складе.
C43: • Налог: база — данные ОПиУ по месяцу продажи (упрощение кассового метода УСН). УСН платится поквартально в месяце после квартала, НПД — в следующем месяце. Взносы ИП и НДС на УСН при превышении порога не считаются — дашборд предупреждает о пороге.
C44: • Окупаемость — месяц, начиная с которого накопленный денежный поток больше не уходит в минус. ROI = чистая прибыль / пик вложенных денег.
B46: Защита и проверка
C47: Листы защищены без пароля, чтобы случайно не стереть формулу. Снять защиту: Рецензирование → Снять защиту листа.
C48: Каждая формула сверена с независимым расчётом на Python (зеркальная модель): расхождение не больше 0,01 ₽. На листе «Денежный поток» есть контроль баланса: деньги + товар + дебиторка − налог = капитал + прибыль.
C49: Лист «Чувствительность» и сравнение сценариев используют «Таблицу данных» Excel (Данные → Анализ «что если»). В Google Таблицах эти две таблицы не пересчитываются.

Sheet Дашборд
B1: Финансовая модель: импорт автотоваров из Китая и продажа на маркетплейсах
B2: Сценарий: | C2: =Сценарий_выбор -> Базовый | E2: Налог: | F2: =Налог_режим -> УСН 6% | H2: Период: | I2: =Дата_начала -> 46327 | K2: по | L2: ='Денежный поток'!W$5 -> 46844
B3: ДЕМО-ДАННЫЕ: все цифры — пример. Ставки пошлин, НДС, налогов и тарифы маркетплейса уточните под свой товар.
B5: ВЫРУЧКА ЗА ПЕРИОД | E5: ЧИСТАЯ ПРИБЫЛЬ | H5: РЕНТАБЕЛЬНОСТЬ ПРОДАЖ | K5: ROI НА ВЛОЖЕННЫЕ ДЕНЬГИ
B6: =ОПиУ!D8 -> 24404970 | E6: =ОПиУ!D46 -> 3052575.5 | H6: =IFERROR(ЧП_итого/Выручка_итого,0) -> 0.12508007 | K6: =IFERROR(ЧП_итого/Пик_вложений,0) -> 1.2730327
B7: выкупы × цена, 18 мес | E7: после налога, 18 мес | H7: чистая прибыль / выручка | K7: чистая прибыль / пик вложений
B9: ПОТРЕБНОСТЬ В ДЕНЬГАХ | E9: МАКС. КАССОВЫЙ РАЗРЫВ | H9: ОКУПАЕМОСТЬ ВЛОЖЕНИЙ | K9: КАПИТАЛ НА КОНЕЦ
B10: =MAX(0,-MIN('Денежный поток'!$F$68:$W$68)) -> 2397876.7 | E10: =MAX('Денежный поток'!$F$66:$W$66) -> 397876.69 | H10: =IFERROR(MATCH(TRUE,'Денежный поток'!$F$70:$W$70,0),"более "&MAX('Денежный поток'!$F$4:$W$4)) -> 16 | K10: ='Денежный поток'!D80 -> 5052575.5
B11: пик вложенных денег | E11: =IFERROR(INDEX('Денежный поток'!$F$5:$W$5,MATCH(TRUE,'Денежный поток'!$F$67:$W$67,0)),"нет") -> 46419 | H11: месяц, с которого деньги не уходят в минус | K11: деньги + товар + дебиторка − налог
B13: =IF(Макс_разрыв>0,"⚠ Кассовый разрыв: в худший месяц не хватает "&FIXED(Макс_разрыв,0)&" ₽. Нужен доп. капитал, меньшие партии или отсрочка оплаты поставщику.","✓ Денег хватает на весь период: кассового разрыва нет.") -> ⚠ Кассовый разрыв: в худший месяц не хватает 397 877 ₽. Нужен доп. капитал, меньшие партии или отсрочка оплаты поставщику.
B14: =IF(COUNTIF('Юнит-экономика'!$C$31:$G$31,"<0")>0,"⚠ Есть товары с убытком на каждой продаже — см. таблицу ниже. ","")&IF(Упущено_шт>0,"⚠ Упущено продаж из-за нехватки товара: "&FIXED(Упущено_шт,0)&" шт. ","")&IF(AND(Налог_номер<3,Выручка_макс_год>Порог_НДС_УСН),"⚠ Выручка за календарный год выше порога НДС для УСН — уточните НДС у бухгалтера. ","")&IF(Налог_номер=3,"⚠ НПД не применяется при перепродаже товаров (422-ФЗ, ст. 4) — режим только для сравнения. ","")&IF(AND(Налог_номер=3,Выручка_макс_год>Лимит_НПД),"⚠ Доход выше лимита НПД. ","")
B15: ="Контроль баланса модели: "&Контроль_баланса&" • остаток денег на конец: "&FIXED(Деньги_конец,0)&" ₽" -> Контроль баланса модели: OK • остаток денег на конец: 2 532 186 ₽
B17: Товар | D17: Цена, ₽ | E17: Себест. на складе МП, ₽ | F17: Прибыль на 1 шт, ₽ | G17: Маржа | H17: ROI на 1 шт | I17: Точка безубыт., шт/мес | J17: План на плато, шт/мес | K17: Продано за период, шт | L17: Выручка за период, ₽ | M17: Упущено, шт
B18: ='Юнит-экономика'!C$4 -> Органайзер в багажник | D18: ='Юнит-экономика'!$C$6 -> 2490 | E18: ='Юнит-экономика'!$C$20 -> 1026.7768 | F18: ='Юнит-экономика'!$C$31 -> 498.20215 | G18: ='Юнит-экономика'!$C$32 -> 0.20008118 | H18: ='Юнит-экономика'!$C$34 -> 0.48520978 | I18: ='Юнит-экономика'!$C$39 -> 21.512512 | J18: ='Юнит-экономика'!$C$36 -> 140 | K18: ='Закупки и склад'!D24 -> 2100 | L18: =ОПиУ!D9 -> 5229000 | M18: ='Закупки и склад'!D32 -> 0
B19: ='Юнит-экономика'!D$4 -> Автопылесос беспроводной | D19: ='Юнит-экономика'!$D$6 -> 2990 | E19: ='Юнит-экономика'!$D$20 -> 1313.3625 | F19: ='Юнит-экономика'!$D$31 -> 617.66355 | G19: ='Юнит-экономика'!$D$32 -> 0.20657644 | H19: ='Юнит-экономика'!$D$34 -> 0.47029174 | I19: ='Юнит-экономика'!$D$39 -> 17.859521 | J19: ='Юнит-экономика'!$D$36 -> 120 | K19: ='Закупки и склад'!D25 -> 1800 | L19: =ОПиУ!D10 -> 5382000 | M19: ='Закупки и склад'!D33 -> 0
B20: ='Юнит-экономика'!E$4 -> Держатель телефона MagSafe | D20: ='Юнит-экономика'!$E$6 -> 1290 | E20: ='Юнит-экономика'!$E$20 -> 473.76547 | F20: ='Юнит-экономика'!$E$31 -> 298.60228 | G20: ='Юнит-экономика'!$E$32 -> 0.23147463 | H20: ='Юнит-экономика'!$E$34 -> 0.63027446 | I20: ='Юнит-экономика'!$E$39 -> 34.533396 | J20: ='Юнит-экономика'!$E$36 -> 260 | K20: ='Закупки и склад'!D26 -> 3900 | L20: =ОПиУ!D11 -> 5031000 | M20: ='Закупки и склад'!D34 -> 0
B21: ='Юнит-экономика'!F$4 -> Чехлы на сиденья, комплект | D21: ='Юнит-экономика'!$F$6 -> 4490 | E21: ='Юнит-экономика'!$F$20 -> 2705.811 | F21: ='Юнит-экономика'!$F$31 -> 52.033444 | G21: ='Юнит-экономика'!$F$32 -> 0.01158874 | H21: ='Юнит-экономика'!$F$34 -> 0.019230258 | I21: ='Юнит-экономика'!$F$39 -> 159.17848 | J21: ='Юнит-экономика'!$F$36 -> 60 | K21: ='Закупки и склад'!D27 -> 900 | L21: =ОПиУ!D12 -> 4041000 | M21: ='Закупки и склад'!D35 -> 0
B22: ='Юнит-экономика'!G$4 -> Видеорегистратор Wi-Fi | D22: ='Юнит-экономика'!$G$6 -> 3490 | E22: ='Юнит-экономика'!$G$20 -> 1710.5292 | F22: ='Юнит-экономика'!$G$31 -> 604.71366 | G22: ='Юнит-экономика'!$G$32 -> 0.17327039 | H22: ='Юнит-экономика'!$G$34 -> 0.35352431 | I22: ='Юнит-экономика'!$G$39 -> 15.96936 | J22: ='Юнит-экономика'!$G$36 -> 90 | K22: ='Закупки и склад'!D28 -> 1353 | L22: =ОПиУ!D13 -> 4721970 | M22: ='Закупки и склад'!D36 -> 0
B23: Итого | K23: =SUM(K18:K22) -> 10053 | L23: =SUM(L18:L22) -> 24404970 | M23: =SUM(M18:M22) -> 0
B25: Остаток денег на счёте, ₽ | F25: Выручка и чистая прибыль по месяцам, ₽ | J25: Из чего складывается цена, ₽ на 1 шт

Sheet Допущения
A1: Допущения — ввод данных
A2: Жёлтые ячейки — ввод (можно менять). Остальные ячейки считаются формулами и защищены. Ставки пошлин, НДС, налогов и тарифы маркетплейса — параметры: уточните их под свой товар.
A3: ДЕМО-ДАННЫЕ: все цифры — пример. Ставки пошлин, НДС, налогов и тарифы маркетплейса уточните под свой товар.
A5: 1. Общие параметры
A6: Параметр | B6: Ед. | C6: Значение | D6: Комментарий
A7: Первый месяц модели (месяц первой оплаты поставщику) | B7: дата | C7: 46327 | D7: Горизонт модели — 18 месяцев с этой даты
A8: Стартовый капитал (свои деньги на счёте) | B8: ₽ | C8: 2000000 | D8: Если остаток денег уходит в минус — это кассовый разрыв
A9: Курс юаня, базовый | B9: ₽ за ¥ | C9: 12 | D9: Сценарии меняют курс относительно этого значения
A10: Комиссия агента / байера в Китае | B10: % товара | C10: 0.03 | D10: Поиск поставщика, выкуп, контроль качества — по договору с агентом
A11: Банк и конвертация при оплате поставщику | B11: % | C11: 0.015 | D11: От суммы «товар + агент»; платёжный агент или банк
A12: Как считать доставку из Китая | B12: список | C12: по большему | D12: по весу / по объёму / по большему из двух — как считает ваш перевозчик
A13: Доставка Китай → склад в РФ, тариф по весу | B13: ₽/кг | C13: 220 | D13: Уточните у карго / экспедитора
A14: Доставка Китай → склад в РФ, тариф по объёму | B14: ₽/м³ | C14: 24000 | D14: Уточните у карго / экспедитора
A15: Таможенное оформление (брокер, сборы) на одну партию товара | B15: ₽/партию | C15: 8000 | D15: Уточните у таможенного брокера. Если карго «под ключ» — 0, а пошлину и НДС на ввоз включите в тариф доставки
A16: Доставка со склада в РФ до склада маркетплейса | B16: ₽/кг | C16: 25 | D16: Фулфилмент / транспортная компания
A17: Обратная логистика маркетплейса за один возврат | B17: ₽/шт | C17: 50 | D17: Уточните по тарифам своей площадки
A18: Реклама на маркетплейсе (доля рекламных расходов) | B18: % выручки | C18: 0.08 | D18: Сценарии добавляют или убавляют п.п.
A19: Постоянные расходы (бухгалтерия, сервисы, персонал) | B19: ₽/мес | C19: 50000 | D19: Каждый месяц с первого
A20: Разовые стартовые расходы (образцы, фото, карточки) | B20: ₽ | C20: 60000 | D20: Списываются в первом месяце
A21: Срок поставки: от оплаты поставщику до склада маркетплейса | B21: мес | C21: 2 | D21: Целое число 1–6. Товар поступает в продажу через столько месяцев после заказа
A22: Страховой запас | B22: мес продаж | C22: 1 | D22: Целое число 0–3. Сколько месяцев продаж держать сверх срока поставки
A23: Задержка выплат маркетплейса после продажи | B23: дней | C23: 14 | D23: 0–120 дней. Дробная часть месяца делится между месяцами
A24: Дней в месяце (для пересчёта задержки выплат) | B24: дней | C24: 30 | D24: Обычно 30
A26: 2. Налоги (ставки — параметры: проверьте свой режим и регион)
A27: Налоговый режим | B27: список | C27: УСН 6% | D27: УСН 6 % — с доходов; УСН 15 % — с доходов минус расходы; НПД — для сравнения
A28: Режим | B28: Ед. | C28: Ставка | D28: Комментарий
A29: УСН 6% | B29: % | C29: 0.06 | D29: Налог с выручки. Базовая ставка; регион может установить ниже — уточните
A30: УСН 15% | B30: % | C30: 0.15 | D30: Налог с разницы «доходы − расходы», считается нарастающим итогом с начала года
A31: НПД | B31: % | C31: 0.06 | D31: Внимание: НПД не применяется при перепродаже товаров (422-ФЗ, ст. 4) — режим оставлен для сравнения
A32: Минимальный налог при УСН 15 % | B32: % доходов | C32: 0.01 | D32: В модели — нарастающим итогом с начала года (консервативно)
A33: Лимит дохода для НПД | B33: ₽/год | C33: 2400000 | D33: Параметр для предупреждения на дашборде — проверьте актуальный лимит
A34: Порог доходов, выше которого УСН платит НДС | B34: ₽/год | C34: 20000000 | D34: Пример — проверьте порог на свой год. НДС на УСН модель не считает, только предупреждает о превышении
A36: 3. Товары (SKU): одна колонка — один товар
A37: Параметр | B37: Ед. | C37: Товар 1 | D37: Товар 2 | E37: Товар 3 | F37: Товар 4 | G37: Товар 5 | H37: Комментарий
A38: Наименование | C38: Органайзер в багажник | D38: Автопылесос беспроводной | E38: Держатель телефона MagSafe | F38: Чехлы на сиденья, комплект | G38: Видеорегистратор Wi-Fi | H38: Короткое название — попадёт в отчёты и графики
A39: Закупочная цена у поставщика | B39: ¥/шт | C39: 32 | D39: 58 | E39: 22 | F39: 105 | G39: 98 | H39: Цена фабрики (EXW/FOB) за единицу
A40: Вес брутто с упаковкой | B40: кг/шт | C40: 1.3 | D40: 1 | E40: 0.3 | F40: 2.6 | G40: 0.4 | H40: Для тарифа доставки по весу
A41: Объём с упаковкой | B41: м³/шт | C41: 0.012 | D41: 0.005 | E41: 0.0012 | F41: 0.018 | G41: 0.0018 | H41: Длина × ширина × высота коробки, м
A42: Партия закупки (кратность заказа) | B42: шт | C42: 200 | D42: 150 | E42: 300 | F42: 100 | G42: 100 | H42: Минимальный заказ у поставщика; модель заказывает кратно партии
A43: Цена продажи на маркетплейсе | B43: ₽ | C43: 2490 | D43: 2990 | E43: 1290 | F43: 4490 | G43: 3490 | H43: Цена, которую платит покупатель (после скидок)
A44: Продажи на плато (выкупы) | B44: шт/мес | C44: 140 | D44: 120 | E44: 260 | F44: 60 | G44: 90 | H44: Сколько штук в месяц покупатели выкупают при 100 % темпа
A45: Остаток на складе МП на старте | B45: шт | C45: 0 | D45: 0 | E45: 0 | F45: 0 | G45: 0 | H45: Если товар уже есть на складе; обычно 0
A46: Ставка пошлины | B46: % тамож. стоим. | C46: 0.1 | D46: 0.05 | E46: 0 | F46: 0.1 | G46: 0 | H46: Уточните по коду ТН ВЭД своего товара
A47: Ставка НДС на ввоз | B47: % | C47: 0.22 | D47: 0.22 | E47: 0.22 | F47: 0.22 | G47: 0.22 | H47: Уточните ставку для своего товара на дату ввоза
A48: Сертификация / декларация соответствия | B48: ₽ разово | C48: 20000 | D48: 45000 | E48: 40000 | F48: 20000 | G48: 50000 | H48: Платится один раз, в месяц первого заказа товара
A49: Упаковка и маркировка | B49: ₽/шт | C49: 35 | D49: 30 | E49: 25 | F49: 45 | G49: 25 | H49: Пакет, этикетка, коды маркировки, если нужны
A50: Комиссия маркетплейса | B50: % цены | C50: 0.2 | D50: 0.18 | E50: 0.2 | F50: 0.2 | G50: 0.17 | H50: Уточните для своей категории и площадки
... A52: Доля возвратов | B52: % заказов | C52: 0.05 | D52: 0.08 | E52: 0.07 | F52: 0.1 | G52: 0.09 | H52: Возвращённый товар возвращается в продажу; платится логистика туда и обратно
A54: 4. Темп продаж по месяцам, % от плато (сезонность и выход на плато)
A55: Месяц | B55: Месяц № | C55: % от плато | D55: Первые месяцы товар едет из Китая — ставьте 0 %, если нет начального остатка
A56: =EDATE(Дата_начала,B56-1) -> 46327 | B56: =ROW()-ROW($B$55) -> 1 | C56: 0
A57: =EDATE(Дата_начала,B57-1) -> 46357 | B57: =ROW()-ROW($B$55) -> 2 | C57: 0
A58: =EDATE(Дата_начала,B58-1) -> 46388 | B58: =ROW()-ROW($B$55) -> 3 | C58: 0.3
A59: =EDATE(Дата_начала,B59-1) -> 46419 | B59: =ROW()-ROW($B$55) -> 4 | C59: 0.5
A60: =EDATE(Дата_начала,B60-1) -> 46447 | B60: =ROW()-ROW($B$55) -> 5 | C60: 0.7
A61: =EDATE(Дата_начала,B61-1) -> 46478 | B61: =ROW()-ROW($B$55) -> 6 | C61: 0.85
A62: =EDATE(Дата_начала,B62-1) -> 46508 | B62: =ROW()-ROW($B$55) -> 7 | C62: 1
A63: =EDATE(Дата_начала,B63-1) -> 46539 | B63: =ROW()-ROW($B$55) -> 8 | C63: 1
A64: =EDATE(Дата_начала,B64-1) -> 46569 | B64: =ROW()-ROW($B$55) -> 9 | C64: 0.95
A65: =EDATE(Дата_начала,B65-1) -> 46600 | B65: =ROW()-ROW($B$55) -> 10 | C65: 1
A66: =EDATE(Дата_начала,B66-1) -> 46631 | B66: =ROW()-ROW($B$55) -> 11 | C66: 1.05
A67: =EDATE(Дата_начала,B67-1) -> 46661 | B67: =ROW()-ROW($B$55) -> 12 | C67: 1.1
... A73: =EDATE(Дата_начала,B73-1) -> 46844 | B73: =ROW()-ROW($B$55) -> 18 | C73: 1.05
A75: 5. Справочник (не менять)
A76: по весу
A77: по объёму
A78: по большему

Sheet Сценарии
A1: Сценарии
A2: Выберите сценарий в жёлтой ячейке — пересчитается вся книга. Базовый = значения листа «Допущения»; остальные сценарии — отклонения от них.
A3: ДЕМО-ДАННЫЕ: все цифры — пример. Ставки пошлин, НДС, налогов и тарифы маркетплейса уточните под свой товар.
A5: Активный сценарий | C5: Базовый
A7: Отклонения от базовых допущений
A8: Параметр | B8: Ед. | C8: Базовый | D8: Пессимистичный | E8: Оптимистичный | F8: Действует сейчас
A9: Курс юаня | B9: % к базе | C9: 0 | D9: 0.15 | E9: -0.05 | F9: =INDEX($C9:$E9,Сценарий_номер) -> 0
A10: Цена продажи | B10: % к базе | C10: 0 | D10: -0.08 | E10: 0.05 | F10: =INDEX($C10:$E10,Сценарий_номер) -> 0
A11: Темп продаж | B11: % к базе | C11: 0 | D11: -0.25 | E11: 0.2 | F11: =INDEX($C11:$E11,Сценарий_номер) -> 0
A12: Реклама (ДРР) | B12: п.п. | C12: 0 | D12: 0.03 | E12: -0.02 | F12: =INDEX($C12:$E12,Сценарий_номер) -> 0
A14: Действующие значения (их использует вся модель)
A15: Курс юаня | B15: ₽ за ¥ | C15: =IF(Курс_анализ>0,Курс_анализ,Курс_база*(1+$F$9)) -> 12
A16: Множитель цены продажи | B16: × | C16: =(1+$F$10)*(1+Цена_анализ) -> 1
A17: Множитель темпа продаж | B17: × | C17: =(1+$F$11)*(1+Объём_анализ) -> 1
A18: Реклама, доля выручки | B18: % | C18: =MAX(0,ДРР_база+$F$12) -> 0.08
A19: Налоговый режим (номер в списке) | B19: № | C19: =MATCH(Налог_режим,Налог_список,0) -> 1
A20: Способ расчёта доставки (номер в списке) | B20: № | C20: =MATCH(Доставка_способ,Доставка_список,0) -> 3
A21: Номер активного сценария | B21: № | C21: =IF(Сценарий_ручной>0,Сценарий_ручной,MATCH(Сценарий_выбор,$C$8:$E$8,0)) -> 1
A22: Служебная: номер сценария для таблицы сравнения (держать 0) | C22: 0
A24: Сравнение сценариев — все три сразу (таблица данных Excel, считается автоматически)
A25: Сценарий | B25: № | C25: Чистая прибыль за 18 мес, ₽ | D25: Выручка за 18 мес, ₽ | E25: Рентабельность продаж | F25: ROI на вложенные деньги | G25: Потребность в деньгах (пик), ₽ | H25: Макс. кассовый разрыв, ₽ | I25: Окупаемость, мес
A26: Текущий расчёт (активный сценарий) | B26: =Сценарий_номер -> 1 | C26: =ЧП_итого -> 3052575.5 | D26: =Выручка_итого -> 24404970 | E26: =Рентабельность -> 0.12508007 | F26: =ROI_период -> 1.2730327 | G26: =Пик_вложений -> 2397876.7 | H26: =Макс_разрыв -> 397876.69 | I26: =Окупаемость_мес -> 16
A27: =INDEX($C$8:$E$8,B27) -> Базовый | B27: 1 | C27: 3052575.5 | D27: 24404970 | E27: 0.12508007 | F27: 1.2730327 | G27: 2397876.7 | H27: 397876.69 | I27: 16
A28: =INDEX($C$8:$E$8,B28) -> Пессимистичный | B28: 2 | C28: -343308.82 | D28: 16862864 | E28: -0.020358868 | F28: -0.11410835 | G28: 3008621.3 | H28: 1008621.3 | I28: более 18
A29: =INDEX($C$8:$E$8,B29) -> Оптимистичный | B29: 3 | C29: 5941978 | D29: 30733720 | E29: 0.19333741 | F29: 2.5329487 | G29: 2345873.8 | H29: 345873.75 | I29: 13
A31: Таблица пересчитывает всю модель для каждого сценария. Если в Excel включён режим «Автоматически, кроме таблиц данных», нажмите F9.

Sheet Юнит-экономика
A1: Юнит-экономика: на 1 проданную единицу
A2: ДЕМО-ДАННЫЕ: все цифры — пример. Ставки пошлин, НДС, налогов и тарифы маркетплейса уточните под свой товар.
A3: ="Сценарий: "&Сценарий_выбор&" • курс "&FIXED(Курс,2)&" ₽/¥ • налог: "&Налог_режим -> Сценарий: Базовый • курс 12,00 ₽/¥ • налог: УСН 6%
A4: Показатель | B4: Ед. | C4: =""&Допущения!$C$38 -> Органайзер в багажник | D4: =""&Допущения!$D$38 -> Автопылесос беспроводной | E4: =""&Допущения!$E$38 -> Держатель телефона MagSafe | F4: =""&Допущения!$F$38 -> Чехлы на сиденья, комплект | G4: =""&Допущения!$G$38 -> Видеорегистратор Wi-Fi
A5: Цена
A6: Цена продажи с учётом сценария | B6: ₽ | C6: =Допущения!$C$43*Множитель_цены -> 2490 | D6: =Допущения!$D$43*Множитель_цены -> 2990 | E6: =Допущения!$E$43*Множитель_цены -> 1290 | F6: =Допущения!$F$43*Множитель_цены -> 4490 | G6: =Допущения!$G$43*Множитель_цены -> 3490
A7: Себестоимость 1 шт до склада маркетплейса
A8: Закупочная цена | B8: ¥ | C8: =Допущения!$C$39 -> 32 | D8: =Допущения!$D$39 -> 58 | E8: =Допущения!$E$39 -> 22 | F8: =Допущения!$F$39 -> 105 | G8: =Допущения!$G$39 -> 98
A9: Курс юаня | B9: ₽/¥ | C9: =Курс -> 12 | D9: =Курс -> 12 | E9: =Курс -> 12 | F9: =Курс -> 12 | G9: =Курс -> 12
A10: Товар | B10: ₽ | C10: =C8*C9 -> 384 | D10: =D8*D9 -> 696 | E10: =E8*E9 -> 264 | F10: =F8*F9 -> 1260 | G10: =G8*G9 -> 1176
A11: Комиссия агента | B11: ₽ | C11: =C10*Комиссия_агента -> 11.52 | D11: =D10*Комиссия_агента -> 20.88 | E11: =E10*Комиссия_агента -> 7.92 | F11: =F10*Комиссия_агента -> 37.8 | G11: =G10*Комиссия_агента -> 35.28
A12: Банк и конвертация | B12: ₽ | C12: =(C10+C11)*Банк_комиссия -> 5.9328 | D12: =(D10+D11)*Банк_комиссия -> 10.7532 | E12: =(E10+E11)*Банк_комиссия -> 4.0788 | F12: =(F10+F11)*Банк_комиссия -> 19.467 | G12: =(G10+G11)*Банк_комиссия -> 18.1692
A13: Доставка Китай → РФ | B13: ₽ | C13: =CHOOSE(Доставка_номер,Допущения!$C$40*Доставка_кг,Допущения!$C$41*Доставка_м3,MAX(Допущения!$C$40*Доставка_кг,Допущения!$C$41*Доставка_м3)) -> 288 | D13: =CHOOSE(Доставка_номер,Допущения!$D$40*Доставка_кг,Допущения!$D$41*Доставка_м3,MAX(Допущения!$D$40*Доставка_кг,Допущения!$D$41*Доставка_м3)) -> 220 | E13: =CHOOSE(Доставка_номер,Допущения!$E$40*Доставка_кг,Допущения!$E$41*Доставка_м3,MAX(Допущения!$E$40*Доставка_кг,Допущения!$E$41*Доставка_м3)) -> 66 | F13: =CHOOSE(Доставка_номер,Допущения!$F$40*Доставка_кг,Допущения!$F$41*Доставка_м3,MAX(Допущения!$F$40*Доставка_кг,Допущения!$F$41*Доставка_м3)) -> 572 | G13: =CHOOSE(Доставка_номер,Допущения!$G$40*Доставка_кг,Допущения!$G$41*Доставка_м3,MAX(Допущения!$G$40*Доставка_кг,Допущения!$G$41*Доставка_м3)) -> 88
A14: Таможенная стоимость (товар + доставка), справочно | B14: ₽ | C14: =C10+C13 -> 672 | D14: =D10+D13 -> 916 | E14: =E10+E13 -> 330 | F14: =F10+F13 -> 1832 | G14: =G10+G13 -> 1264
A15: Пошлина | B15: ₽ | C15: =C14*Допущения!$C$46 -> 67.2 | D15: =D14*Допущения!$D$46 -> 45.8 | E15: =E14*Допущения!$E$46 -> 0 | F15: =F14*Допущения!$F$46 -> 183.2 | G15: =G14*Допущения!$G$46 -> 0
A16: НДС на ввоз | B16: ₽ | C16: =(C14+C15)*Допущения!$C$47 -> 162.624 | D16: =(D14+D15)*Допущения!$D$47 -> 211.596 | E16: =(E14+E15)*Допущения!$E$47 -> 72.6 | F16: =(F14+F15)*Допущения!$F$47 -> 443.344 | G16: =(G14+G15)*Допущения!$G$47 -> 278.08
A17: Таможенное оформление на 1 шт | B17: ₽ | C17: =IFERROR(Тамож_оформление/Допущения!$C$42,0) -> 40 | D17: =IFERROR(Тамож_оформление/Допущения!$D$42,0) -> 53.333333 | E17: =IFERROR(Тамож_оформление/Допущения!$E$42,0) -> 26.666667 | F17: =IFERROR(Тамож_оформление/Допущения!$F$42,0) -> 80 | G17: =IFERROR(Тамож_оформление/Допущения!$G$42,0) -> 80
A18: Упаковка и маркировка | B18: ₽ | C18: =Допущения!$C$49 -> 35 | D18: =Допущения!$D$49 -> 30 | E18: =Допущения!$E$49 -> 25 | F18: =Допущения!$F$49 -> 45 | G18: =Допущения!$G$49 -> 25
A19: Доставка до склада маркетплейса | B19: ₽ | C19: =Допущения!$C$40*Доставка_до_МП -> 32.5 | D19: =Допущения!$D$40*Доставка_до_МП -> 25 | E19: =Допущения!$E$40*Доставка_до_МП -> 7.5 | F19: =Допущения!$F$40*Доставка_до_МП -> 65 | G19: =Допущения!$G$40*Доставка_до_МП -> 10
A20: Себестоимость 1 шт на складе маркетплейса | B20: ₽ | C20: =C10+C11+C12+C13+C15+C16+C17+C18+C19 -> 1026.7768 | D20: =D10+D11+D12+D13+D15+D16+D17+D18+D19 -> 1313.3625 | E20: =E10+E11+E12+E13+E15+E16+E17+E18+E19 -> 473.76547 | F20: =F10+F11+F12+F13+F15+F16+F17+F18+F19 -> 2705.811 | G20: =G10+G11+G12+G13+G15+G16+G17+G18+G19 -> 1710.5292
A21: в т.ч. платится при заказе (товар, агент, банк) | B21: ₽ | C21: =C10+C11+C12 -> 401.4528 | D21: =D10+D11+D12 -> 727.6332 | E21: =E10+E11+E12 -> 275.9988 | F21: =F10+F11+F12 -> 1317.267 | G21: =G10+G11+G12 -> 1229.4492
A22: в т.ч. платится при поступлении (доставка, таможня, подготовка) | B22: ₽ | C22: =C20-C21 -> 625.324 | D22: =D20-D21 -> 585.72933 | E22: =E20-E21 -> 197.76667 | F22: =F20-F21 -> 1388.544 | G22: =G20-G21 -> 481.08
A23: Расходы на продажу, на 1 выкупленную шт
A24: Комиссия маркетплейса | B24: ₽ | C24: =C6*Допущения!$C$50 -> 498 | D24: =D6*Допущения!$D$50 -> 538.2 | E24: =E6*Допущения!$E$50 -> 258 | F24: =F6*Допущения!$F$50 -> 898 | G24: =G6*Допущения!$G$50 -> 593.3
A25: Логистика маркетплейса с учётом возвратов | B25: ₽ | C25: =(Допущения!$C$51+Допущения!$C$52*Возврат_логистика)/(1-Допущения!$C$52) -> 118.42105 | D25: =(Допущения!$D$51+Допущения!$D$52*Возврат_логистика)/(1-Допущения!$D$52) -> 102.17391 | E25: =(Допущения!$E$51+Допущения!$E$52*Возврат_логистика)/(1-Допущения!$E$52) -> 79.032258 | F25: =(Допущения!$F$51+Допущения!$F$52*Возврат_логистика)/(1-Допущения!$F$52) -> 205.55556 | G25: =(Допущения!$G$51+Допущения!$G$52*Возврат_логистика)/(1-Допущения!$G$52) -> 92.857143
A26: Реклама | B26: ₽ | C26: =C6*ДРР -> 199.2 | D26: =D6*ДРР -> 239.2 | E26: =E6*ДРР -> 103.2 | F26: =F6*ДРР -> 359.2 | G26: =G6*ДРР -> 279.2
A27: Прибыль до налога | B27: ₽ | C27: =C6-C20-C24-C25-C26 -> 647.60215 | D27: =D6-D20-D24-D25-D26 -> 797.06355 | E27: =E6-E20-E24-E25-E26 -> 376.00228 | F27: =F6-F20-F24-F25-F26 -> 321.43344 | G27: =G6-G20-G24-G25-G26 -> 814.11366
A28: Налог | B28: ₽ | C28: =CHOOSE(Налог_номер,C6*Ставка_УСН6,MAX(C27*Ставка_УСН15,C6*Мин_налог_УСН15),C6*Ставка_НПД) -> 149.4 | D28: =CHOOSE(Налог_номер,D6*Ставка_УСН6,MAX(D27*Ставка_УСН15,D6*Мин_налог_УСН15),D6*Ставка_НПД) -> 179.4 | E28: =CHOOSE(Налог_номер,E6*Ставка_УСН6,MAX(E27*Ставка_УСН15,E6*Мин_налог_УСН15),E6*Ставка_НПД) -> 77.4 | F28: =CHOOSE(Налог_номер,F6*Ставка_УСН6,MAX(F27*Ставка_УСН15,F6*Мин_налог_УСН15),F6*Ставка_НПД) -> 269.4 | G28: =CHOOSE(Налог_номер,G6*Ставка_УСН6,MAX(G27*Ставка_УСН15,G6*Мин_налог_УСН15),G6*Ставка_НПД) -> 209.4
A29: Полная себестоимость продажи | B29: ₽ | C29: =C20+C24+C25+C26+C28 -> 1991.7979 | D29: =D20+D24+D25+D26+D28 -> 2372.3364 | E29: =E20+E24+E25+E26+E28 -> 991.39772 | F29: =F20+F24+F25+F26+F28 -> 4437.9666 | G29: =G20+G24+G25+G26+G28 -> 2885.2863
A30: Результат на 1 шт
A31: Прибыль на 1 шт | B31: ₽ | C31: =C6-C29 -> 498.20215 | D31: =D6-D29 -> 617.66355 | E31: =E6-E29 -> 298.60228 | F31: =F6-F29 -> 52.033444 | G31: =G6-G29 -> 604.71366
A32: Маржа (прибыль / цена) | B32: % | C32: =IFERROR(C31/C6,0) -> 0.20008118 | D32: =IFERROR(D31/D6,0) -> 0.20657644 | E32: =IFERROR(E31/E6,0) -> 0.23147463 | F32: =IFERROR(F31/F6,0) -> 0.01158874 | G32: =IFERROR(G31/G6,0) -> 0.17327039
A33: Наценка к себестоимости на складе МП | B33: % | C33: =IFERROR((C6-C20)/C20,0) -> 1.4250645 | D33: =IFERROR((D6-D20)/D20,0) -> 1.2765991 | E33: =IFERROR((E6-E20)/E20,0) -> 1.7228663 | F33: =IFERROR((F6-F20)/F20,0) -> 0.65939158 | G33: =IFERROR((G6-G20)/G20,0) -> 1.0403043
A34: ROI на вложенный рубль (прибыль / себестоимость) | B34: % | C34: =IFERROR(C31/C20,0) -> 0.48520978 | D34: =IFERROR(D31/D20,0) -> 0.47029174 | E34: =IFERROR(E31/E20,0) -> 0.63027446 | F34: =IFERROR(F31/F20,0) -> 0.019230258 | G34: =IFERROR(G31/G20,0) -> 0.35352431
A35: Безубыточность
A36: План продаж на плато с учётом сценария | B36: шт/мес | C36: =Допущения!$C$44*Множитель_продаж -> 140 | D36: =Допущения!$D$44*Множитель_продаж -> 120 | E36: =Допущения!$E$44*Множитель_продаж -> 260 | F36: =Допущения!$F$44*Множитель_продаж -> 60 | G36: =Допущения!$G$44*Множитель_продаж -> 90
A37: Доля товара в выручке на плато | B37: % | C37: =IFERROR(C6*Допущения!$C$44/SUMPRODUCT($C$6:$G$6,Допущения!$C$44:$G$44),0) -> 0.2143516 | D37: =IFERROR(D6*Допущения!$D$44/SUMPRODUCT($C$6:$G$6,Допущения!$C$44:$G$44),0) -> 0.2206235 | E37: =IFERROR(E6*Допущения!$E$44/SUMPRODUCT($C$6:$G$6,Допущения!$C$44:$G$44),0) -> 0.20623501 | F37: =IFERROR(F6*Допущения!$F$44/SUMPRODUCT($C$6:$G$6,Допущения!$C$44:$G$44),0) -> 0.16565209 | G37: =IFERROR(G6*Допущения!$G$44/SUMPRODUCT($C$6:$G$6,Допущения!$C$44:$G$44),0) -> 0.1931378
A38: Постоянные расходы, приходящиеся на товар | B38: ₽/мес | C38: =Пост_расходы*C37 -> 10717.58 | D38: =Пост_расходы*D37 -> 11031.175 | E38: =Пост_расходы*E37 -> 10311.751 | F38: =Пост_расходы*F37 -> 8282.6047 | G38: =Пост_расходы*G37 -> 9656.8899
A39: Точка безубыточности (покрыть свои постоянные расходы) | B39: шт/мес | C39: =IF(C31>0,C38/C31,"убыток на ед.") -> 21.512512 | D39: =IF(D31>0,D38/D31,"убыток на ед.") -> 17.859521 | E39: =IF(E31>0,E38/E31,"убыток на ед.") -> 34.533396 | F39: =IF(F31>0,F38/F31,"убыток на ед.") -> 159.17848 | G39: =IF(G31>0,G38/G31,"убыток на ед.") -> 15.96936
A40: Сертификация окупается за | B40: шт | C40: =IF(C31>0,Допущения!$C$48/C31,"—") -> 40.144347 | D40: =IF(D31>0,Допущения!$D$48/D31,"—") -> 72.855197 | E40: =IF(E31>0,Допущения!$E$48/E31,"—") -> 133.95745 | F40: =IF(F31>0,Допущения!$F$48/F31,"—") -> 384.36817 | G40: =IF(G31>0,Допущения!$G$48/G31,"—") -> 82.683762

Sheet Закупки и склад
A1: Закупки и склад: штуки по месяцам
A2: Логика заказа: каждый месяц модель проверяет остаток + товар в пути. Если их не хватает на продажи за срок поставки + страховой запас — заказывает партии (кратно партии SKU). Заказ приходит через «Срок поставки» месяцев.
A3: ДЕМО-ДАННЫЕ: все цифры — пример. Ставки пошлин, НДС, налогов и тарифы маркетплейса уточните под свой товар.
A4: Месяц № | F4: =COLUMN()-COLUMN($E$4) -> 1 | G4: =COLUMN()-COLUMN($E$4) -> 2 | H4: =COLUMN()-COLUMN($E$4) -> 3 | I4: =COLUMN()-COLUMN($E$4) -> 4 | J4: =COLUMN()-COLUMN($E$4) -> 5 | K4: =COLUMN()-COLUMN($E$4) -> 6 | L4: =COLUMN()-COLUMN($E$4) -> 7 | M4: =COLUMN()-COLUMN($E$4) -> 8 | ... W4: =COLUMN()-COLUMN($E$4) -> 18
A5: Показатель | B5: Ед. | C5: Параметр | D5: Итого | E5: Старт | F5: =EDATE(Дата_начала,F$4-1) -> 46327 | G5: =EDATE(Дата_начала,G$4-1) -> 46357 | H5: =EDATE(Дата_начала,H$4-1) -> 46388 | I5: =EDATE(Дата_начала,I$4-1) -> 46419 | J5: =EDATE(Дата_начала,J$4-1) -> 46447 | K5: =EDATE(Дата_начала,K$4-1) -> 46478 | L5: =EDATE(Дата_начала,L$4-1) -> 46508 | M5: =EDATE(Дата_начала,M$4-1) -> 46539 | ... W5: =EDATE(Дата_начала,W$4-1) -> 46844
A7: 1. Спрос: план выкупов | C7: плато, шт/мес
A8: =""&Допущения!$C$38 -> Органайзер в багажник | B8: шт | C8: =Допущения!$C$44 -> 140 | D8: =SUM(F8:W8) -> 2100 | F8: =ROUND($C8*INDEX(Темп_продаж,F$4)*Множитель_продаж,0) -> 0 | G8: =ROUND($C8*INDEX(Темп_продаж,G$4)*Множитель_продаж,0) -> 0 | H8: =ROUND($C8*INDEX(Темп_продаж,H$4)*Множитель_продаж,0) -> 42 | I8: =ROUND($C8*INDEX(Темп_продаж,I$4)*Множитель_продаж,0) -> 70 | J8: =ROUND($C8*INDEX(Темп_продаж,J$4)*Множитель_продаж,0) -> 98 | K8: =ROUND($C8*INDEX(Темп_продаж,K$4)*Множитель_продаж,0) -> 119 | L8: =ROUND($C8*INDEX(Темп_продаж,L$4)*Множитель_продаж,0) -> 140 | M8: =ROUND($C8*INDEX(Темп_продаж,M$4)*Множитель_продаж,0) -> 140 | ... W8: =ROUND($C8*INDEX(Темп_продаж,W$4)*Множитель_продаж,0) -> 147
A9: =""&Допущения!$D$38 -> Автопылесос беспроводной | B9: шт | C9: =Допущения!$D$44 -> 120 | D9: =SUM(F9:W9) -> 1800 | F9: =ROUND($C9*INDEX(Темп_продаж,F$4)*Множитель_продаж,0) -> 0 | G9: =ROUND($C9*INDEX(Темп_продаж,G$4)*Множитель_продаж,0) -> 0 | H9: =ROUND($C9*INDEX(Темп_продаж,H$4)*Множитель_продаж,0) -> 36 | I9: =ROUND($C9*INDEX(Темп_продаж,I$4)*Множитель_продаж,0) -> 60 | J9: =ROUND($C9*INDEX(Темп_продаж,J$4)*Множитель_продаж,0) -> 84 | K9: =ROUND($C9*INDEX(Темп_продаж,K$4)*Множитель_продаж,0) -> 102 | L9: =ROUND($C9*INDEX(Темп_продаж,L$4)*Множитель_продаж,0) -> 120 | M9: =ROUND($C9*INDEX(Темп_продаж,M$4)*Множитель_продаж,0) -> 120 | ... W9: =ROUND($C9*INDEX(Темп_продаж,W$4)*Множитель_продаж,0) -> 126
A10: =""&Допущения!$E$38 -> Держатель телефона MagSafe | B10: шт | C10: =Допущения!$E$44 -> 260 | D10: =SUM(F10:W10) -> 3900 | F10: =ROUND($C10*INDEX(Темп_продаж,F$4)*Множитель_продаж,0) -> 0 | G10: =ROUND($C10*INDEX(Темп_продаж,G$4)*Множитель_продаж,0) -> 0 | H10: =ROUND($C10*INDEX(Темп_продаж,H$4)*Множитель_продаж,0) -> 78 | I10: =ROUND($C10*INDEX(Темп_продаж,I$4)*Множитель_продаж,0) -> 130 | J10: =ROUND($C10*INDEX(Темп_продаж,J$4)*Множитель_продаж,0) -> 182 | K10: =ROUND($C10*INDEX(Темп_продаж,K$4)*Множитель_продаж,0) -> 221 | L10: =ROUND($C10*INDEX(Темп_продаж,L$4)*Множитель_продаж,0) -> 260 | M10: =ROUND($C10*INDEX(Темп_продаж,M$4)*Множитель_продаж,0) -> 260 | ... W10: =ROUND($C10*INDEX(Темп_продаж,W$4)*Множитель_продаж,0) -> 273
A11: =""&Допущения!$F$38 -> Чехлы на сиденья, комплект | B11: шт | C11: =Допущения!$F$44 -> 60 | D11: =SUM(F11:W11) -> 900 | F11: =ROUND($C11*INDEX(Темп_продаж,F$4)*Множитель_продаж,0) -> 0 | G11: =ROUND($C11*INDEX(Темп_продаж,G$4)*Множитель_продаж,0) -> 0 | H11: =ROUND($C11*INDEX(Темп_продаж,H$4)*Множитель_продаж,0) -> 18 | I11: =ROUND($C11*INDEX(Темп_продаж,I$4)*Множитель_продаж,0) -> 30 | J11: =ROUND($C11*INDEX(Темп_продаж,J$4)*Множитель_продаж,0) -> 42 | K11: =ROUND($C11*INDEX(Темп_продаж,K$4)*Множитель_продаж,0) -> 51 | L11: =ROUND($C11*INDEX(Темп_продаж,L$4)*Множитель_продаж,0) -> 60 | M11: =ROUND($C11*INDEX(Темп_продаж,M$4)*Множитель_продаж,0) -> 60 | ... W11: =ROUND($C11*INDEX(Темп_продаж,W$4)*Множитель_продаж,0) -> 63
A12: =""&Допущения!$G$38 -> Видеорегистратор Wi-Fi | B12: шт | C12: =Допущения!$G$44 -> 90 | D12: =SUM(F12:W12) -> 1353 | F12: =ROUND($C12*INDEX(Темп_продаж,F$4)*Множитель_продаж,0) -> 0 | G12: =ROUND($C12*INDEX(Темп_продаж,G$4)*Множитель_продаж,0) -> 0 | H12: =ROUND($C12*INDEX(Темп_продаж,H$4)*Множитель_продаж,0) -> 27 | I12: =ROUND($C12*INDEX(Темп_продаж,I$4)*Множитель_продаж,0) -> 45 | J12: =ROUND($C12*INDEX(Темп_продаж,J$4)*Множитель_продаж,0) -> 63 | K12: =ROUND($C12*INDEX(Темп_продаж,K$4)*Множитель_продаж,0) -> 77 | L12: =ROUND($C12*INDEX(Темп_продаж,L$4)*Множитель_продаж,0) -> 90 | M12: =ROUND($C12*INDEX(Темп_продаж,M$4)*Множитель_продаж,0) -> 90 | ... W12: =ROUND($C12*INDEX(Темп_продаж,W$4)*Множитель_продаж,0) -> 95
A13: Итого | B13: шт | D13: =SUM(F13:W13) -> 10053 | F13: =SUM(F8:F12) -> 0 | G13: =SUM(G8:G12) -> 0 | H13: =SUM(H8:H12) -> 201 | I13: =SUM(I8:I12) -> 335 | J13: =SUM(J8:J12) -> 469 | K13: =SUM(K8:K12) -> 570 | L13: =SUM(L8:L12) -> 670 | M13: =SUM(M8:M12) -> 670 | ... W13: =SUM(W8:W12) -> 704
A15: 2. Поступление на склад маркетплейса
A16: =""&Допущения!$C$38 -> Органайзер в багажник | B16: шт | D16: =SUM(F16:W16) -> 2400 | F16: =SUMIFS($E$71:E$71,$E$4:E$4,F$4-Срок_поставки) -> 0 | G16: =SUMIFS($E$71:F$71,$E$4:F$4,G$4-Срок_поставки) -> 0 | H16: =SUMIFS($E$71:G$71,$E$4:G$4,H$4-Срок_поставки) -> 200 | I16: =SUMIFS($E$71:H$71,$E$4:H$4,I$4-Срок_поставки) -> 200 | J16: =SUMIFS($E$71:I$71,$E$4:I$4,J$4-Срок_поставки) -> 0 | K16: =SUMIFS($E$71:J$71,$E$4:J$4,K$4-Срок_поставки) -> 200 | L16: =SUMIFS($E$71:K$71,$E$4:K$4,L$4-Срок_поставки) -> 200 | M16: =SUMIFS($E$71:L$71,$E$4:L$4,M$4-Срок_поставки) -> 0 | ... W16: =SUMIFS($E$71:V$71,$E$4:V$4,W$4-Срок_поставки) -> 200
A17: =""&Допущения!$D$38 -> Автопылесос беспроводной | B17: шт | D17: =SUM(F17:W17) -> 1950 | F17: =SUMIFS($E$72:E$72,$E$4:E$4,F$4-Срок_поставки) -> 0 | G17: =SUMIFS($E$72:F$72,$E$4:F$4,G$4-Срок_поставки) -> 0 | H17: =SUMIFS($E$72:G$72,$E$4:G$4,H$4-Срок_поставки) -> 150 | I17: =SUMIFS($E$72:H$72,$E$4:H$4,I$4-Срок_поставки) -> 150 | J17: =SUMIFS($E$72:I$72,$E$4:I$4,J$4-Срок_поставки) -> 0 | K17: =SUMIFS($E$72:J$72,$E$4:J$4,K$4-Срок_поставки) -> 150 | L17: =SUMIFS($E$72:K$72,$E$4:K$4,L$4-Срок_поставки) -> 150 | M17: =SUMIFS($E$72:L$72,$E$4:L$4,M$4-Срок_поставки) -> 150 | ... W17: =SUMIFS($E$72:V$72,$E$4:V$4,W$4-Срок_поставки) -> 150
A18: =""&Допущения!$E$38 -> Держатель телефона MagSafe | B18: шт | D18: =SUM(F18:W18) -> 4200 | F18: =SUMIFS($E$73:E$73,$E$4:E$4,F$4-Срок_поставки) -> 0 | G18: =SUMIFS($E$73:F$73,$E$4:F$4,G$4-Срок_поставки) -> 0 | H18: =SUMIFS($E$73:G$73,$E$4:G$4,H$4-Срок_поставки) -> 300 | I18: =SUMIFS($E$73:H$73,$E$4:H$4,I$4-Срок_поставки) -> 300 | J18: =SUMIFS($E$73:I$73,$E$4:I$4,J$4-Срок_поставки) -> 300 | K18: =SUMIFS($E$73:J$73,$E$4:J$4,K$4-Срок_поставки) -> 0 | L18: =SUMIFS($E$73:K$73,$E$4:K$4,L$4-Срок_поставки) -> 300 | M18: =SUMIFS($E$73:L$73,$E$4:L$4,M$4-Срок_поставки) -> 300 | ... W18: =SUMIFS($E$73:V$73,$E$4:V$4,W$4-Срок_поставки) -> 300
A19: =""&Допущения!$F$38 -> Чехлы на сиденья, комплект | B19: шт | D19: =SUM(F19:W19) -> 1000 | F19: =SUMIFS($E$74:E$74,$E$4:E$4,F$4-Срок_поставки) -> 0 | G19: =SUMIFS($E$74:F$74,$E$4:F$4,G$4-Срок_поставки) -> 0 | H19: =SUMIFS($E$74:G$74,$E$4:G$4,H$4-Срок_поставки) -> 100 | I19: =SUMIFS($E$74:H$74,$E$4:H$4,I$4-Срок_поставки) -> 0 | J19: =SUMIFS($E$74:I$74,$E$4:I$4,J$4-Срок_поставки) -> 100 | K19: =SUMIFS($E$74:J$74,$E$4:J$4,K$4-Срок_поставки) -> 100 | L19: =SUMIFS($E$74:K$74,$E$4:K$4,L$4-Срок_поставки) -> 0 | M19: =SUMIFS($E$74:L$74,$E$4:L$4,M$4-Срок_поставки) -> 100 | ... W19: =SUMIFS($E$74:V$74,$E$4:V$4,W$4-Срок_поставки) -> 100
A20: =""&Допущения!$G$38 -> Видеорегистратор Wi-Fi | B20: шт | D20: =SUM(F20:W20) -> 1500 | F20: =SUMIFS($E$75:E$75,$E$4:E$4,F$4-Срок_поставки) -> 0 | G20: =SUMIFS($E$75:F$75,$E$4:F$4,G$4-Срок_поставки) -> 0 | H20: =SUMIFS($E$75:G$75,$E$4:G$4,H$4-Срок_поставки) -> 100 | I20: =SUMIFS($E$75:H$75,$E$4:H$4,I$4-Срок_поставки) -> 100 | J20: =SUMIFS($E$75:I$75,$E$4:I$4,J$4-Срок_поставки) -> 100 | K20: =SUMIFS($E$75:J$75,$E$4:J$4,K$4-Срок_поставки) -> 100 | L20: =SUMIFS($E$75:K$75,$E$4:K$4,L$4-Срок_поставки) -> 0 | M20: =SUMIFS($E$75:L$75,$E$4:L$4,M$4-Срок_поставки) -> 100 | ... W20: =SUMIFS($E$75:V$75,$E$4:V$4,W$4-Срок_поставки) -> 100
A21: Итого | B21: шт | D21: =SUM(F21:W21) -> 11050 | F21: =SUM(F16:F20) -> 0 | G21: =SUM(G16:G20) -> 0 | H21: =SUM(H16:H20) -> 850 | I21: =SUM(I16:I20) -> 750 | J21: =SUM(J16:J20) -> 500 | K21: =SUM(K16:K20) -> 550 | L21: =SUM(L16:L20) -> 650 | M21: =SUM(M16:M20) -> 650 | ... W21: =SUM(W16:W20) -> 850
A23: 3. Продажи (выкупы) = min(спрос, доступный товар)
A24: =""&Допущения!$C$38 -> Органайзер в багажник | B24: шт | D24: =SUM(F24:W24) -> 2100 | F24: =MIN(F8,E40+F16) -> 0 | G24: =MIN(G8,F40+G16) -> 0 | H24: =MIN(H8,G40+H16) -> 42 | I24: =MIN(I8,H40+I16) -> 70 | J24: =MIN(J8,I40+J16) -> 98 | K24: =MIN(K8,J40+K16) -> 119 | L24: =MIN(L8,K40+L16) -> 140 | M24: =MIN(M8,L40+M16) -> 140 | ... W24: =MIN(W8,V40+W16) -> 147
A25: =""&Допущения!$D$38 -> Автопылесос беспроводной | B25: шт | D25: =SUM(F25:W25) -> 1800 | F25: =MIN(F9,E41+F17) -> 0 | G25: =MIN(G9,F41+G17) -> 0 | H25: =MIN(H9,G41+H17) -> 36 | I25: =MIN(I9,H41+I17) -> 60 | J25: =MIN(J9,I41+J17) -> 84 | K25: =MIN(K9,J41+K17) -> 102 | L25: =MIN(L9,K41+L17) -> 120 | M25: =MIN(M9,L41+M17) -> 120 | ... W25: =MIN(W9,V41+W17) -> 126
A26: =""&Допущения!$E$38 -> Держатель телефона MagSafe | B26: шт | D26: =SUM(F26:W26) -> 3900 | F26: =MIN(F10,E42+F18) -> 0 | G26: =MIN(G10,F42+G18) -> 0 | H26: =MIN(H10,G42+H18) -> 78 | I26: =MIN(I10,H42+I18) -> 130 | J26: =MIN(J10,I42+J18) -> 182 | K26: =MIN(K10,J42+K18) -> 221 | L26: =MIN(L10,K42+L18) -> 260 | M26: =MIN(M10,L42+M18) -> 260 | ... W26: =MIN(W10,V42+W18) -> 273
A27: =""&Допущения!$F$38 -> Чехлы на сиденья, комплект | B27: шт | D27: =SUM(F27:W27) -> 900 | F27: =MIN(F11,E43+F19) -> 0 | G27: =MIN(G11,F43+G19) -> 0 | H27: =MIN(H11,G43+H19) -> 18 | I27: =MIN(I11,H43+I19) -> 30 | J27: =MIN(J11,I43+J19) -> 42 | K27: =MIN(K11,J43+K19) -> 51 | L27: =MIN(L11,K43+L19) -> 60 | M27: =MIN(M11,L43+M19) -> 60 | ... W27: =MIN(W11,V43+W19) -> 63
A28: =""&Допущения!$G$38 -> Видеорегистратор Wi-Fi | B28: шт | D28: =SUM(F28:W28) -> 1353 | F28: =MIN(F12,E44+F20) -> 0 | G28: =MIN(G12,F44+G20) -> 0 | H28: =MIN(H12,G44+H20) -> 27 | I28: =MIN(I12,H44+I20) -> 45 | J28: =MIN(J12,I44+J20) -> 63 | K28: =MIN(K12,J44+K20) -> 77 | L28: =MIN(L12,K44+L20) -> 90 | M28: =MIN(M12,L44+M20) -> 90 | ... W28: =MIN(W12,V44+W20) -> 95
A29: Итого | B29: шт | D29: =SUM(F29:W29) -> 10053 | F29: =SUM(F24:F28) -> 0 | G29: =SUM(G24:G28) -> 0 | H29: =SUM(H24:H28) -> 201 | I29: =SUM(I24:I28) -> 335 | J29: =SUM(J24:J28) -> 469 | K29: =SUM(K24:K28) -> 570 | L29: =SUM(L24:L28) -> 670 | M29: =SUM(M24:M28) -> 670 | ... W29: =SUM(W24:W28) -> 704
A31: 4. Упущенные продажи — товара не было
A32: =""&Допущения!$C$38 -> Органайзер в багажник | B32: шт | D32: =SUM(F32:W32) -> 0 | F32: =F8-F24 -> 0 | G32: =G8-G24 -> 0 | H32: =H8-H24 -> 0 | I32: =I8-I24 -> 0 | J32: =J8-J24 -> 0 | K32: =K8-K24 -> 0 | L32: =L8-L24 -> 0 | M32: =M8-M24 -> 0 | ... W32: =W8-W24 -> 0
A33: =""&Допущения!$D$38 -> Автопылесос беспроводной | B33: шт | D33: =SUM(F33:W33) -> 0 | F33: =F9-F25 -> 0 | G33: =G9-G25 -> 0 | H33: =H9-H25 -> 0 | I33: =I9-I25 -> 0 | J33: =J9-J25 -> 0 | K33: =K9-K25 -> 0 | L33: =L9-L25 -> 0 | M33: =M9-M25 -> 0 | ... W33: =W9-W25 -> 0
A34: =""&Допущения!$E$38 -> Держатель телефона MagSafe | B34: шт | D34: =SUM(F34:W34) -> 0 | F34: =F10-F26 -> 0 | G34: =G10-G26 -> 0 | H34: =H10-H26 -> 0 | I34: =I10-I26 -> 0 | J34: =J10-J26 -> 0 | K34: =K10-K26 -> 0 | L34: =L10-L26 -> 0 | M34: =M10-M26 -> 0 | ... W34: =W10-W26 -> 0
A35: =""&Допущения!$F$38 -> Чехлы на сиденья, комплект | B35: шт | D35: =SUM(F35:W35) -> 0 | F35: =F11-F27 -> 0 | G35: =G11-G27 -> 0 | H35: =H11-H27 -> 0 | I35: =I11-I27 -> 0 | J35: =J11-J27 -> 0 | K35: =K11-K27 -> 0 | L35: =L11-L27 -> 0 | M35: =M11-M27 -> 0 | ... W35: =W11-W27 -> 0
A36: =""&Допущения!$G$38 -> Видеорегистратор Wi-Fi | B36: шт | D36: =SUM(F36:W36) -> 0 | F36: =F12-F28 -> 0 | G36: =G12-G28 -> 0 | H36: =H12-H28 -> 0 | I36: =I12-I28 -> 0 | J36: =J12-J28 -> 0 | K36: =K12-K28 -> 0 | L36: =L12-L28 -> 0 | M36: =M12-M28 -> 0 | ... W36: =W12-W28 -> 0
A37: Итого | B37: шт | D37: =SUM(F37:W37) -> 0 | F37: =SUM(F32:F36) -> 0 | G37: =SUM(G32:G36) -> 0 | H37: =SUM(H32:H36) -> 0 | I37: =SUM(I32:I36) -> 0 | J37: =SUM(J32:J36) -> 0 | K37: =SUM(K32:K36) -> 0 | L37: =SUM(L32:L36) -> 0 | M37: =SUM(M32:M36) -> 0 | ... W37: =SUM(W32:W36) -> 0
A39: 5. Остаток на складе на конец месяца | C39: себест. 1 шт, ₽
A40: =""&Допущения!$C$38 -> Органайзер в багажник | B40: шт | C40: ='Юнит-экономика'!$C$20 -> 1026.7768 | E40: =Допущения!$C$45 -> 0 | F40: =E40+F16-F24 -> 0 | G40: =F40+G16-G24 -> 0 | H40: =G40+H16-H24 -> 158 | I40: =H40+I16-I24 -> 288 | J40: =I40+J16-J24 -> 190 | K40: =J40+K16-K24 -> 271 | L40: =K40+L16-L24 -> 331 | M40: =L40+M16-M24 -> 191 | ... W40: =V40+W16-W24 -> 300
A41: =""&Допущения!$D$38 -> Автопылесос беспроводной | B41: шт | C41: ='Юнит-экономика'!$D$20 -> 1313.3625 | E41: =Допущения!$D$45 -> 0 | F41: =E41+F17-F25 -> 0 | G41: =F41+G17-G25 -> 0 | H41: =G41+H17-H25 -> 114 | I41: =H41+I17-I25 -> 204 | J41: =I41+J17-J25 -> 120 | K41: =J41+K17-K25 -> 168 | L41: =K41+L17-L25 -> 198 | M41: =L41+M17-M25 -> 228 | ... W41: =V41+W17-W25 -> 150
A42: =""&Допущения!$E$38 -> Держатель телефона MagSafe | B42: шт | C42: ='Юнит-экономика'!$E$20 -> 473.76547 | E42: =Допущения!$E$45 -> 0 | F42: =E42+F18-F26 -> 0 | G42: =F42+G18-G26 -> 0 | H42: =G42+H18-H26 -> 222 | I42: =H42+I18-I26 -> 392 | J42: =I42+J18-J26 -> 510 | K42: =J42+K18-K26 -> 289 | L42: =K42+L18-L26 -> 329 | M42: =L42+M18-M26 -> 369 | ... W42: =V42+W18-W26 -> 300
A43: =""&Допущения!$F$38 -> Чехлы на сиденья, комплект | B43: шт | C43: ='Юнит-экономика'!$F$20 -> 2705.811 | E43: =Допущения!$F$45 -> 0 | F43: =E43+F19-F27 -> 0 | G43: =F43+G19-G27 -> 0 | H43: =G43+H19-H27 -> 82 | I43: =H43+I19-I27 -> 52 | J43: =I43+J19-J27 -> 110 | K43: =J43+K19-K27 -> 159 | L43: =K43+L19-L27 -> 99 | M43: =L43+M19-M27 -> 139 | ... W43: =V43+W19-W27 -> 100
A44: =""&Допущения!$G$38 -> Видеорегистратор Wi-Fi | B44: шт | C44: ='Юнит-экономика'!$G$20 -> 1710.5292 | E44: =Допущения!$G$45 -> 0 | F44: =E44+F20-F28 -> 0 | G44: =F44+G20-G28 -> 0 | H44: =G44+H20-H28 -> 73 | I44: =H44+I20-I28 -> 128 | J44: =I44+J20-J28 -> 165 | K44: =J44+K20-K28 -> 188 | L44: =K44+L20-L28 -> 98 | M44: =L44+M20-M28 -> 108 | ... W44: =V44+W20-W28 -> 147
A45: Итого | B45: шт | E45: =SUM(E40:E44) -> 0 | F45: =SUM(F40:F44) -> 0 | G45: =SUM(G40:G44) -> 0 | H45: =SUM(H40:H44) -> 649 | I45: =SUM(I40:I44) -> 1064 | J45: =SUM(J40:J44) -> 1095 | K45: =SUM(K40:K44) -> 1075 | L45: =SUM(L40:L44) -> 1055 | ... W45: =SUM(W40:W44) -> 997
A46: Стоимость запаса по себестоимости | B46: ₽ | E46: =SUMPRODUCT(E40:E44,$C40:$C44) -> 0 | F46: =SUMPRODUCT(F40:F44,$C40:$C44) -> 0 | G46: =SUMPRODUCT(G40:G44,$C40:$C44) -> 0 | H46: =SUMPRODUCT(H40:H44,$C40:$C44) -> 763875.13 | I46: =SUMPRODUCT(I40:I44,$C40:$C44) -> 1109003.6 | J46: =SUMPRODUCT(J40:J44,$C40:$C44) -> 1174188 | K46: =SUMPRODUCT(K40:K44,$C40:$C44) -> 1387623.1 | L46: =SUMPRODUCT(L40:L44,$C40:$C44) -> 1191284.9 | ... W46: =SUMPRODUCT(W40:W44,$C40:$C44) -> 1169196
A48: 6. Товар в пути (заказан, ещё не поступил) | C48: оплачено за 1 шт, ₽
A49: =""&Допущения!$C$38 -> Органайзер в багажник | B49: шт | C49: ='Юнит-экономика'!$C$21 -> 401.4528 | F49: =SUMIFS($E$71:E$71,$E$4:E$4,">"&(F$4-Срок_поставки)) -> 0 | G49: =SUMIFS($E$71:F$71,$E$4:F$4,">"&(G$4-Срок_поставки)) -> 200 | H49: =SUMIFS($E$71:G$71,$E$4:G$4,">"&(H$4-Срок_поставки)) -> 200 | I49: =SUMIFS($E$71:H$71,$E$4:H$4,">"&(I$4-Срок_поставки)) -> 0 | J49: =SUMIFS($E$71:I$71,$E$4:I$4,">"&(J$4-Срок_поставки)) -> 200 | K49: =SUMIFS($E$71:J$71,$E$4:J$4,">"&(K$4-Срок_поставки)) -> 200 | L49: =SUMIFS($E$71:K$71,$E$4:K$4,">"&(L$4-Срок_поставки)) -> 0 | M49: =SUMIFS($E$71:L$71,$E$4:L$4,">"&(M$4-Срок_поставки)) -> 200 | ... W49: =SUMIFS($E$71:V$71,$E$4:V$4,">"&(W$4-Срок_поставки)) -> 0
A50: =""&Допущения!$D$38 -> Автопылесос беспроводной | B50: шт | C50: ='Юнит-экономика'!$D$21 -> 727.6332 | F50: =SUMIFS($E$72:E$72,$E$4:E$4,">"&(F$4-Срок_поставки)) -> 0 | G50: =SUMIFS($E$72:F$72,$E$4:F$4,">"&(G$4-Срок_поставки)) -> 150 | H50: =SUMIFS($E$72:G$72,$E$4:G$4,">"&(H$4-Срок_поставки)) -> 150 | I50: =SUMIFS($E$72:H$72,$E$4:H$4,">"&(I$4-Срок_поставки)) -> 0 | J50: =SUMIFS($E$72:I$72,$E$4:I$4,">"&(J$4-Срок_поставки)) -> 150 | K50: =SUMIFS($E$72:J$72,$E$4:J$4,">"&(K$4-Срок_поставки)) -> 150 | L50: =SUMIFS($E$72:K$72,$E$4:K$4,">"&(L$4-Срок_поставки)) -> 150 | M50: =SUMIFS($E$72:L$72,$E$4:L$4,">"&(M$4-Срок_поставки)) -> 150 | ... W50: =SUMIFS($E$72:V$72,$E$4:V$4,">"&(W$4-Срок_поставки)) -> 150
A51: =""&Допущения!$E$38 -> Держатель телефона MagSafe | B51: шт | C51: ='Юнит-экономика'!$E$21 -> 275.9988 | F51: =SUMIFS($E$73:E$73,$E$4:E$4,">"&(F$4-Срок_поставки)) -> 0 | G51: =SUMIFS($E$73:F$73,$E$4:F$4,">"&(G$4-Срок_поставки)) -> 300 | H51: =SUMIFS($E$73:G$73,$E$4:G$4,">"&(H$4-Срок_поставки)) -> 300 | I51: =SUMIFS($E$73:H$73,$E$4:H$4,">"&(I$4-Срок_поставки)) -> 300 | J51: =SUMIFS($E$73:I$73,$E$4:I$4,">"&(J$4-Срок_поставки)) -> 0 | K51: =SUMIFS($E$73:J$73,$E$4:J$4,">"&(K$4-Срок_поставки)) -> 300 | L51: =SUMIFS($E$73:K$73,$E$4:K$4,">"&(L$4-Срок_поставки)) -> 300 | M51: =SUMIFS($E$73:L$73,$E$4:L$4,">"&(M$4-Срок_поставки)) -> 300 | ... W51: =SUMIFS($E$73:V$73,$E$4:V$4,">"&(W$4-Срок_поставки)) -> 300
A52: =""&Допущения!$F$38 -> Чехлы на сиденья, комплект | B52: шт | C52: ='Юнит-экономика'!$F$21 -> 1317.267 | F52: =SUMIFS($E$74:E$74,$E$4:E$4,">"&(F$4-Срок_поставки)) -> 0 | G52: =SUMIFS($E$74:F$74,$E$4:F$4,">"&(G$4-Срок_поставки)) -> 100 | H52: =SUMIFS($E$74:G$74,$E$4:G$4,">"&(H$4-Срок_поставки)) -> 0 | I52: =SUMIFS($E$74:H$74,$E$4:H$4,">"&(I$4-Срок_поставки)) -> 100 | J52: =SUMIFS($E$74:I$74,$E$4:I$4,">"&(J$4-Срок_поставки)) -> 100 | K52: =SUMIFS($E$74:J$74,$E$4:J$4,">"&(K$4-Срок_поставки)) -> 0 | L52: =SUMIFS($E$74:K$74,$E$4:K$4,">"&(L$4-Срок_поставки)) -> 100 | M52: =SUMIFS($E$74:L$74,$E$4:L$4,">"&(M$4-Срок_поставки)) -> 0 | ... W52: =SUMIFS($E$74:V$74,$E$4:V$4,">"&(W$4-Срок_поставки)) -> 100
A53: =""&Допущения!$G$38 -> Видеорегистратор Wi-Fi | B53: шт | C53: ='Юнит-экономика'!$G$21 -> 1229.4492 | F53: =SUMIFS($E$75:E$75,$E$4:E$4,">"&(F$4-Срок_поставки)) -> 0 | G53: =SUMIFS($E$75:F$75,$E$4:F$4,">"&(G$4-Срок_поставки)) -> 100 | H53: =SUMIFS($E$75:G$75,$E$4:G$4,">"&(H$4-Срок_поставки)) -> 100 | I53: =SUMIFS($E$75:H$75,$E$4:H$4,">"&(I$4-Срок_поставки)) -> 100 | J53: =SUMIFS($E$75:I$75,$E$4:I$4,">"&(J$4-Срок_поставки)) -> 100 | K53: =SUMIFS($E$75:J$75,$E$4:J$4,">"&(K$4-Срок_поставки)) -> 0 | L53: =SUMIFS($E$75:K$75,$E$4:K$4,">"&(L$4-Срок_поставки)) -> 100 | M53: =SUMIFS($E$75:L$75,$E$4:L$4,">"&(M$4-Срок_поставки)) -> 100 | ... W53: =SUMIFS($E$75:V$75,$E$4:V$4,">"&(W$4-Срок_поставки)) -> 100
A54: Итого | B54: шт | F54: =SUM(F49:F53) -> 0 | G54: =SUM(G49:G53) -> 850 | H54: =SUM(H49:H53) -> 750 | I54: =SUM(I49:I53) -> 500 | J54: =SUM(J49:J53) -> 550 | K54: =SUM(K49:K53) -> 650 | L54: =SUM(L49:L53) -> 650 | M54: =SUM(M49:M53) -> 750 | ... W54: =SUM(W49:W53) -> 650
A56: 7. Нужно на срок поставки + страховой запас
A57: =""&Допущения!$C$38 -> Органайзер в багажник | B57: шт | F57: =SUMIFS($F8:$W8,$F$4:$W$4,">"&F$4,$F$4:$W$4,"<="&(F$4+Срок_поставки+Страх_запас))+MAX(0,F$4+Срок_поставки+Страх_запас-$W$4)*$W8 -> 112 | G57: =SUMIFS($F8:$W8,$F$4:$W$4,">"&G$4,$F$4:$W$4,"<="&(G$4+Срок_поставки+Страх_запас))+MAX(0,G$4+Срок_поставки+Страх_запас-$W$4)*$W8 -> 210 | H57: =SUMIFS($F8:$W8,$F$4:$W$4,">"&H$4,$F$4:$W$4,"<="&(H$4+Срок_поставки+Страх_запас))+MAX(0,H$4+Срок_поставки+Страх_запас-$W$4)*$W8 -> 287 | I57: =SUMIFS($F8:$W8,$F$4:$W$4,">"&I$4,$F$4:$W$4,"<="&(I$4+Срок_поставки+Страх_запас))+MAX(0,I$4+Срок_поставки+Страх_запас-$W$4)*$W8 -> 357 | J57: =SUMIFS($F8:$W8,$F$4:$W$4,">"&J$4,$F$4:$W$4,"<="&(J$4+Срок_поставки+Страх_запас))+MAX(0,J$4+Срок_поставки+Страх_запас-$W$4)*$W8 -> 399 | K57: =SUMIFS($F8:$W8,$F$4:$W$4,">"&K$4,$F$4:$W$4,"<="&(K$4+Срок_поставки+Страх_запас))+MAX(0,K$4+Срок_поставки+Страх_запас-$W$4)*$W8 -> 413 | L57: =SUMIFS($F8:$W8,$F$4:$W$4,">"&L$4,$F$4:$W$4,"<="&(L$4+Срок_поставки+Страх_запас))+MAX(0,L$4+Срок_поставки+Страх_запас-$W$4)*$W8 -> 413 | M57: =SUMIFS($F8:$W8,$F$4:$W$4,">"&M$4,$F$4:$W$4,"<="&(M$4+Срок_поставки+Страх_запас))+MAX(0,M$4+Срок_поставки+Страх_запас-$W$4)*$W8 -> 420 | ... W57: =SUMIFS($F8:$W8,$F$4:$W$4,">"&W$4,$F$4:$W$4,"<="&(W$4+Срок_поставки+Страх_запас))+MAX(0,W$4+Срок_поставки+Страх_запас-$W$4)*$W8 -> 441
A58: =""&Допущения!$D$38 -> Автопылесос беспроводной | B58: шт | F58: =SUMIFS($F9:$W9,$F$4:$W$4,">"&F$4,$F$4:$W$4,"<="&(F$4+Срок_поставки+Страх_запас))+MAX(0,F$4+Срок_поставки+Страх_запас-$W$4)*$W9 -> 96 | G58: =SUMIFS($F9:$W9,$F$4:$W$4,">"&G$4,$F$4:$W$4,"<="&(G$4+Срок_поставки+Страх_запас))+MAX(0,G$4+Срок_поставки+Страх_запас-$W$4)*$W9 -> 180 | H58: =SUMIFS($F9:$W9,$F$4:$W$4,">"&H$4,$F$4:$W$4,"<="&(H$4+Срок_поставки+Страх_запас))+MAX(0,H$4+Срок_поставки+Страх_запас-$W$4)*$W9 -> 246 | I58: =SUMIFS($F9:$W9,$F$4:$W$4,">"&I$4,$F$4:$W$4,"<="&(I$4+Срок_поставки+Страх_запас))+MAX(0,I$4+Срок_поставки+Страх_запас-$W$4)*$W9 -> 306 | J58: =SUMIFS($F9:$W9,$F$4:$W$4,">"&J$4,$F$4:$W$4,"<="&(J$4+Срок_поставки+Страх_запас))+MAX(0,J$4+Срок_поставки+Страх_запас-$W$4)*$W9 -> 342 | K58: =SUMIFS($F9:$W9,$F$4:$W$4,">"&K$4,$F$4:$W$4,"<="&(K$4+Срок_поставки+Страх_запас))+MAX(0,K$4+Срок_поставки+Страх_запас-$W$4)*$W9 -> 354 | L58: =SUMIFS($F9:$W9,$F$4:$W$4,">"&L$4,$F$4:$W$4,"<="&(L$4+Срок_поставки+Страх_запас))+MAX(0,L$4+Срок_поставки+Страх_запас-$W$4)*$W9 -> 354 | M58: =SUMIFS($F9:$W9,$F$4:$W$4,">"&M$4,$F$4:$W$4,"<="&(M$4+Срок_поставки+Страх_запас))+MAX(0,M$4+Срок_поставки+Страх_запас-$W$4)*$W9 -> 360 | ... W58: =SUMIFS($F9:$W9,$F$4:$W$4,">"&W$4,$F$4:$W$4,"<="&(W$4+Срок_поставки+Страх_запас))+MAX(0,W$4+Срок_поставки+Страх_запас-$W$4)*$W9 -> 378
A59: =""&Допущения!$E$38 -> Держатель телефона MagSafe | B59: шт | F59: =SUMIFS($F10:$W10,$F$4:$W$4,">"&F$4,$F$4:$W$4,"<="&(F$4+Срок_поставки+Страх_запас))+MAX(0,F$4+Срок_поставки+Страх_запас-$W$4)*$W10 -> 208 | G59: =SUMIFS($F10:$W10,$F$4:$W$4,">"&G$4,$F$4:$W$4,"<="&(G$4+Срок_поставки+Страх_запас))+MAX(0,G$4+Срок_поставки+Страх_запас-$W$4)*$W10 -> 390 | H59: =SUMIFS($F10:$W10,$F$4:$W$4,">"&H$4,$F$4:$W$4,"<="&(H$4+Срок_поставки+Страх_запас))+MAX(0,H$4+Срок_поставки+Страх_запас-$W$4)*$W10 -> 533 | I59: =SUMIFS($F10:$W10,$F$4:$W$4,">"&I$4,$F$4:$W$4,"<="&(I$4+Срок_поставки+Страх_запас))+MAX(0,I$4+Срок_поставки+Страх_запас-$W$4)*$W10 -> 663 | J59: =SUMIFS($F10:$W10,$F$4:$W$4,">"&J$4,$F$4:$W$4,"<="&(J$4+Срок_поставки+Страх_запас))+MAX(0,J$4+Срок_поставки+Страх_запас-$W$4)*$W10 -> 741 | K59: =SUMIFS($F10:$W10,$F$4:$W$4,">"&K$4,$F$4:$W$4,"<="&(K$4+Срок_поставки+Страх_запас))+MAX(0,K$4+Срок_поставки+Страх_запас-$W$4)*$W10 -> 767 | L59: =SUMIFS($F10:$W10,$F$4:$W$4,">"&L$4,$F$4:$W$4,"<="&(L$4+Срок_поставки+Страх_запас))+MAX(0,L$4+Срок_поставки+Страх_запас-$W$4)*$W10 -> 767 | M59: =SUMIFS($F10:$W10,$F$4:$W$4,">"&M$4,$F$4:$W$4,"<="&(M$4+Срок_поставки+Страх_запас))+MAX(0,M$4+Срок_поставки+Страх_запас-$W$4)*$W10 -> 780 | ... W59: =SUMIFS($F10:$W10,$F$4:$W$4,">"&W$4,$F$4:$W$4,"<="&(W$4+Срок_поставки+Страх_запас))+MAX(0,W$4+Срок_поставки+Страх_запас-$W$4)*$W10 -> 819
A60: =""&Допущения!$F$38 -> Чехлы на сиденья, комплект | B60: шт | F60: =SUMIFS($F11:$W11,$F$4:$W$4,">"&F$4,$F$4:$W$4,"<="&(F$4+Срок_поставки+Страх_запас))+MAX(0,F$4+Срок_поставки+Страх_запас-$W$4)*$W11 -> 48 | G60: =SUMIFS($F11:$W11,$F$4:$W$4,">"&G$4,$F$4:$W$4,"<="&(G$4+Срок_поставки+Страх_запас))+MAX(0,G$4+Срок_поставки+Страх_запас-$W$4)*$W11 -> 90 | H60: =SUMIFS($F11:$W11,$F$4:$W$4,">"&H$4,$F$4:$W$4,"<="&(H$4+Срок_поставки+Страх_запас))+MAX(0,H$4+Срок_поставки+Страх_запас-$W$4)*$W11 -> 123 | I60: =SUMIFS($F11:$W11,$F$4:$W$4,">"&I$4,$F$4:$W$4,"<="&(I$4+Срок_поставки+Страх_запас))+MAX(0,I$4+Срок_поставки+Страх_запас-$W$4)*$W11 -> 153 | J60: =SUMIFS($F11:$W11,$F$4:$W$4,">"&J$4,$F$4:$W$4,"<="&(J$4+Срок_поставки+Страх_запас))+MAX(0,J$4+Срок_поставки+Страх_запас-$W$4)*$W11 -> 171 | K60: =SUMIFS($F11:$W11,$F$4:$W$4,">"&K$4,$F$4:$W$4,"<="&(K$4+Срок_поставки+Страх_запас))+MAX(0,K$4+Срок_поставки+Страх_запас-$W$4)*$W11 -> 177 | L60: =SUMIFS($F11:$W11,$F$4:$W$4,">"&L$4,$F$4:$W$4,"<="&(L$4+Срок_поставки+Страх_запас))+MAX(0,L$4+Срок_поставки+Страх_запас-$W$4)*$W11 -> 177 | M60: =SUMIFS($F11:$W11,$F$4:$W$4,">"&M$4,$F$4:$W$4,"<="&(M$4+Срок_поставки+Страх_запас))+MAX(0,M$4+Срок_поставки+Страх_запас-$W$4)*$W11 -> 180 | ... W60: =SUMIFS($F11:$W11,$F$4:$W$4,">"&W$4,$F$4:$W$4,"<="&(W$4+Срок_поставки+Страх_запас))+MAX(0,W$4+Срок_поставки+Страх_запас-$W$4)*$W11 -> 189
A61: =""&Допущения!$G$38 -> Видеорегистратор Wi-Fi | B61: шт | F61: =SUMIFS($F12:$W12,$F$4:$W$4,">"&F$4,$F$4:$W$4,"<="&(F$4+Срок_поставки+Страх_запас))+MAX(0,F$4+Срок_поставки+Страх_запас-$W$4)*$W12 -> 72 | G61: =SUMIFS($F12:$W12,$F$4:$W$4,">"&G$4,$F$4:$W$4,"<="&(G$4+Срок_поставки+Страх_запас))+MAX(0,G$4+Срок_поставки+Страх_запас-$W$4)*$W12 -> 135 | H61: =SUMIFS($F12:$W12,$F$4:$W$4,">"&H$4,$F$4:$W$4,"<="&(H$4+Срок_поставки+Страх_запас))+MAX(0,H$4+Срок_поставки+Страх_запас-$W$4)*$W12 -> 185 | I61: =SUMIFS($F12:$W12,$F$4:$W$4,">"&I$4,$F$4:$W$4,"<="&(I$4+Срок_поставки+Страх_запас))+MAX(0,I$4+Срок_поставки+Страх_запас-$W$4)*$W12 -> 230 | J61: =SUMIFS($F12:$W12,$F$4:$W$4,">"&J$4,$F$4:$W$4,"<="&(J$4+Срок_поставки+Страх_запас))+MAX(0,J$4+Срок_поставки+Страх_запас-$W$4)*$W12 -> 257 | K61: =SUMIFS($F12:$W12,$F$4:$W$4,">"&K$4,$F$4:$W$4,"<="&(K$4+Срок_поставки+Страх_запас))+MAX(0,K$4+Срок_поставки+Страх_запас-$W$4)*$W12 -> 266 | L61: =SUMIFS($F12:$W12,$F$4:$W$4,">"&L$4,$F$4:$W$4,"<="&(L$4+Срок_поставки+Страх_запас))+MAX(0,L$4+Срок_поставки+Страх_запас-$W$4)*$W12 -> 266 | M61: =SUMIFS($F12:$W12,$F$4:$W$4,">"&M$4,$F$4:$W$4,"<="&(M$4+Срок_поставки+Страх_запас))+MAX(0,M$4+Срок_поставки+Страх_запас-$W$4)*$W12 -> 271 | ... W61: =SUMIFS($F12:$W12,$F$4:$W$4,">"&W$4,$F$4:$W$4,"<="&(W$4+Срок_поставки+Страх_запас))+MAX(0,W$4+Срок_поставки+Страх_запас-$W$4)*$W12 -> 285
A63: 8. Заказ поставщику, партий | C63: партия, шт
A64: =""&Допущения!$C$38 -> Органайзер в багажник | B64: партий | C64: =Допущения!$C$42 -> 200 | D64: =SUM(F64:W64) -> 13 | F64: =IF(F57-F40-F49>0,ROUNDUP((F57-F40-F49)/$C64,0),0) -> 1 | G64: =IF(G57-G40-G49>0,ROUNDUP((G57-G40-G49)/$C64,0),0) -> 1 | H64: =IF(H57-H40-H49>0,ROUNDUP((H57-H40-H49)/$C64,0),0) -> 0 | I64: =IF(I57-I40-I49>0,ROUNDUP((I57-I40-I49)/$C64,0),0) -> 1 | J64: =IF(J57-J40-J49>0,ROUNDUP((J57-J40-J49)/$C64,0),0) -> 1 | K64: =IF(K57-K40-K49>0,ROUNDUP((K57-K40-K49)/$C64,0),0) -> 0 | L64: =IF(L57-L40-L49>0,ROUNDUP((L57-L40-L49)/$C64,0),0) -> 1 | M64: =IF(M57-M40-M49>0,ROUNDUP((M57-M40-M49)/$C64,0),0) -> 1 | ... W64: =IF(W57-W40-W49>0,ROUNDUP((W57-W40-W49)/$C64,0),0) -> 1
A65: =""&Допущения!$D$38 -> Автопылесос беспроводной | B65: партий | C65: =Допущения!$D$42 -> 150 | D65: =SUM(F65:W65) -> 15 | F65: =IF(F58-F41-F50>0,ROUNDUP((F58-F41-F50)/$C65,0),0) -> 1 | G65: =IF(G58-G41-G50>0,ROUNDUP((G58-G41-G50)/$C65,0),0) -> 1 | H65: =IF(H58-H41-H50>0,ROUNDUP((H58-H41-H50)/$C65,0),0) -> 0 | I65: =IF(I58-I41-I50>0,ROUNDUP((I58-I41-I50)/$C65,0),0) -> 1 | J65: =IF(J58-J41-J50>0,ROUNDUP((J58-J41-J50)/$C65,0),0) -> 1 | K65: =IF(K58-K41-K50>0,ROUNDUP((K58-K41-K50)/$C65,0),0) -> 1 | L65: =IF(L58-L41-L50>0,ROUNDUP((L58-L41-L50)/$C65,0),0) -> 1 | M65: =IF(M58-M41-M50>0,ROUNDUP((M58-M41-M50)/$C65,0),0) -> 0 | ... W65: =IF(W58-W41-W50>0,ROUNDUP((W58-W41-W50)/$C65,0),0) -> 1
A66: =""&Допущения!$E$38 -> Держатель телефона MagSafe | B66: партий | C66: =Допущения!$E$42 -> 300 | D66: =SUM(F66:W66) -> 16 | F66: =IF(F59-F42-F51>0,ROUNDUP((F59-F42-F51)/$C66,0),0) -> 1 | G66: =IF(G59-G42-G51>0,ROUNDUP((G59-G42-G51)/$C66,0),0) -> 1 | H66: =IF(H59-H42-H51>0,ROUNDUP((H59-H42-H51)/$C66,0),0) -> 1 | I66: =IF(I59-I42-I51>0,ROUNDUP((I59-I42-I51)/$C66,0),0) -> 0 | J66: =IF(J59-J42-J51>0,ROUNDUP((J59-J42-J51)/$C66,0),0) -> 1 | K66: =IF(K59-K42-K51>0,ROUNDUP((K59-K42-K51)/$C66,0),0) -> 1 | L66: =IF(L59-L42-L51>0,ROUNDUP((L59-L42-L51)/$C66,0),0) -> 1 | M66: =IF(M59-M42-M51>0,ROUNDUP((M59-M42-M51)/$C66,0),0) -> 1 | ... W66: =IF(W59-W42-W51>0,ROUNDUP((W59-W42-W51)/$C66,0),0) -> 1
A67: =""&Допущения!$F$38 -> Чехлы на сиденья, комплект | B67: партий | C67: =Допущения!$F$42 -> 100 | D67: =SUM(F67:W67) -> 11 | F67: =IF(F60-F43-F52>0,ROUNDUP((F60-F43-F52)/$C67,0),0) -> 1 | G67: =IF(G60-G43-G52>0,ROUNDUP((G60-G43-G52)/$C67,0),0) -> 0 | H67: =IF(H60-H43-H52>0,ROUNDUP((H60-H43-H52)/$C67,0),0) -> 1 | I67: =IF(I60-I43-I52>0,ROUNDUP((I60-I43-I52)/$C67,0),0) -> 1 | J67: =IF(J60-J43-J52>0,ROUNDUP((J60-J43-J52)/$C67,0),0) -> 0 | K67: =IF(K60-K43-K52>0,ROUNDUP((K60-K43-K52)/$C67,0),0) -> 1 | L67: =IF(L60-L43-L52>0,ROUNDUP((L60-L43-L52)/$C67,0),0) -> 0 | M67: =IF(M60-M43-M52>0,ROUNDUP((M60-M43-M52)/$C67,0),0) -> 1 | ... W67: =IF(W60-W43-W52>0,ROUNDUP((W60-W43-W52)/$C67,0),0) -> 0
A68: =""&Допущения!$G$38 -> Видеорегистратор Wi-Fi | B68: партий | C68: =Допущения!$G$42 -> 100 | D68: =SUM(F68:W68) -> 17 | F68: =IF(F61-F44-F53>0,ROUNDUP((F61-F44-F53)/$C68,0),0) -> 1 | G68: =IF(G61-G44-G53>0,ROUNDUP((G61-G44-G53)/$C68,0),0) -> 1 | H68: =IF(H61-H44-H53>0,ROUNDUP((H61-H44-H53)/$C68,0),0) -> 1 | I68: =IF(I61-I44-I53>0,ROUNDUP((I61-I44-I53)/$C68,0),0) -> 1 | J68: =IF(J61-J44-J53>0,ROUNDUP((J61-J44-J53)/$C68,0),0) -> 0 | K68: =IF(K61-K44-K53>0,ROUNDUP((K61-K44-K53)/$C68,0),0) -> 1 | L68: =IF(L61-L44-L53>0,ROUNDUP((L61-L44-L53)/$C68,0),0) -> 1 | M68: =IF(M61-M44-M53>0,ROUNDUP((M61-M44-M53)/$C68,0),0) -> 1 | ... W68: =IF(W61-W44-W53>0,ROUNDUP((W61-W44-W53)/$C68,0),0) -> 1
A70: 9. Заказ поставщику, штук | C70: партия, шт
A71: =""&Допущения!$C$38 -> Органайзер в багажник | B71: шт | C71: =Допущения!$C$42 -> 200 | D71: =SUM(F71:W71) -> 2600 | F71: =F64*$C71 -> 200 | G71: =G64*$C71 -> 200 | H71: =H64*$C71 -> 0 | I71: =I64*$C71 -> 200 | J71: =J64*$C71 -> 200 | K71: =K64*$C71 -> 0 | L71: =L64*$C71 -> 200 | M71: =M64*$C71 -> 200 | ... W71: =W64*$C71 -> 200
A72: =""&Допущения!$D$38 -> Автопылесос беспроводной | B72: шт | C72: =Допущения!$D$42 -> 150 | D72: =SUM(F72:W72) -> 2250 | F72: =F65*$C72 -> 150 | G72: =G65*$C72 -> 150 | H72: =H65*$C72 -> 0 | I72: =I65*$C72 -> 150 | J72: =J65*$C72 -> 150 | K72: =K65*$C72 -> 150 | L72: =L65*$C72 -> 150 | M72: =M65*$C72 -> 0 | ... W72: =W65*$C72 -> 150
A73: =""&Допущения!$E$38 -> Держатель телефона MagSafe | B73: шт | C73: =Допущения!$E$42 -> 300 | D73: =SUM(F73:W73) -> 4800 | F73: =F66*$C73 -> 300 | G73: =G66*$C73 -> 300 | H73: =H66*$C73 -> 300 | I73: =I66*$C73 -> 0 | J73: =J66*$C73 -> 300 | K73: =K66*$C73 -> 300 | L73: =L66*$C73 -> 300 | M73: =M66*$C73 -> 300 | ... W73: =W66*$C73 -> 300
A74: =""&Допущения!$F$38 -> Чехлы на сиденья, комплект | B74: шт | C74: =Допущения!$F$42 -> 100 | D74: =SUM(F74:W74) -> 1100 | F74: =F67*$C74 -> 100 | G74: =G67*$C74 -> 0 | H74: =H67*$C74 -> 100 | I74: =I67*$C74 -> 100 | J74: =J67*$C74 -> 0 | K74: =K67*$C74 -> 100 | L74: =L67*$C74 -> 0 | M74: =M67*$C74 -> 100 | ... W74: =W67*$C74 -> 0
A75: =""&Допущения!$G$38 -> Видеорегистратор Wi-Fi | B75: шт | C75: =Допущения!$G$42 -> 100 | D75: =SUM(F75:W75) -> 1700 | F75: =F68*$C75 -> 100 | G75: =G68*$C75 -> 100 | H75: =H68*$C75 -> 100 | I75: =I68*$C75 -> 100 | J75: =J68*$C75 -> 0 | K75: =K68*$C75 -> 100 | L75: =L68*$C75 -> 100 | M75: =M68*$C75 -> 100 | ... W75: =W68*$C75 -> 100
A76: Итого | B76: шт | D76: =SUM(F76:W76) -> 12450 | F76: =SUM(F71:F75) -> 850 | G76: =SUM(G71:G75) -> 750 | H76: =SUM(H71:H75) -> 500 | I76: =SUM(I71:I75) -> 550 | J76: =SUM(J71:J75) -> 650 | K76: =SUM(K71:K75) -> 650 | L76: =SUM(L71:L75) -> 750 | M76: =SUM(M71:M75) -> 700 | ... W76: =SUM(W71:W75) -> 750

Sheet Денежный поток
A1: Денежный поток по месяцам
A2: Покупка товара — деньги уходят при заказе (товар) и при поступлении (доставка, таможня). Выручка приходит с задержкой выплат маркетплейса. Красным — месяцы, когда денег не хватает (кассовый разрыв).
A3: ДЕМО-ДАННЫЕ: все цифры — пример. Ставки пошлин, НДС, налогов и тарифы маркетплейса уточните под свой товар.
A4: Месяц № | F4: =COLUMN()-COLUMN($E$4) -> 1 | G4: =COLUMN()-COLUMN($E$4) -> 2 | H4: =COLUMN()-COLUMN($E$4) -> 3 | I4: =COLUMN()-COLUMN($E$4) -> 4 | J4: =COLUMN()-COLUMN($E$4) -> 5 | K4: =COLUMN()-COLUMN($E$4) -> 6 | L4: =COLUMN()-COLUMN($E$4) -> 7 | M4: =COLUMN()-COLUMN($E$4) -> 8 | ... W4: =COLUMN()-COLUMN($E$4) -> 18
A5: Показатель | B5: Ед. | C5: Параметр | D5: Итого | E5: Старт | F5: =EDATE(Дата_начала,F$4-1) -> 46327 | G5: =EDATE(Дата_начала,G$4-1) -> 46357 | H5: =EDATE(Дата_начала,H$4-1) -> 46388 | I5: =EDATE(Дата_начала,I$4-1) -> 46419 | J5: =EDATE(Дата_начала,J$4-1) -> 46447 | K5: =EDATE(Дата_начала,K$4-1) -> 46478 | L5: =EDATE(Дата_начала,L$4-1) -> 46508 | M5: =EDATE(Дата_начала,M$4-1) -> 46539 | ... W5: =EDATE(Дата_начала,W$4-1) -> 46844
A7: Остаток денег на начало месяца | B7: ₽ | F7: =E65 -> 2000000 | G7: =F65 -> 1188093.2 | H7: =G65 -> 742913.1 | I7: =H65 -> 56803.691 | J7: =I65 -> -315376.47 | K7: =J65 -> -218123.59 | L7: =K65 -> -397876.69 | M7: =L65 -> -84529.663 | ... W7: =V65 -> 2549951
A9: ПОСТУПЛЕНИЯ
A10: Задержка выплат: целых месяцев (служебная) | C10: =INT(Задержка_выплат_дн/Дней_в_месяце) -> 0
A11: Доля выплат, которая приходит ещё на месяц позже (служебная) | C11: =Задержка_выплат_дн/Дней_в_месяце-$C$10 -> 0.46666667
A12: Начислено маркетплейсом к выплате (выручка − комиссия − логистика) | B12: ₽ | D12: =SUM(F12:W12) -> 18721816 | F12: =ОПиУ!F8-ОПиУ!F23-ОПиУ!F29 -> 0 | G12: =ОПиУ!G8-ОПиУ!G23-ОПиУ!G29 -> 0 | H12: =ОПиУ!H8-ОПиУ!H23-ОПиУ!H29 -> 374268.1 | I12: =ОПиУ!I8-ОПиУ!I23-ОПиУ!I29 -> 623780.16 | J12: =ОПиУ!J8-ОПиУ!J23-ОПиУ!J29 -> 873292.22 | K12: =ОПиУ!K8-ОПиУ!K23-ОПиУ!K29 -> 1061828.2 | L12: =ОПиУ!L8-ОПиУ!L23-ОПиУ!L29 -> 1247560.3 | M12: =ОПиУ!M8-ОПиУ!M23-ОПиУ!M29 -> 1247560.3 | ... W12: =ОПиУ!W8-ОПиУ!W23-ОПиУ!W29 -> 1311340.3
A13: Выплаты маркетплейса | B13: ₽ | D13: =SUM(F13:W13) -> 18109858 | F13: =(1-$C$11)*SUMIFS($F$12:$W$12,$F$4:$W$4,F$4-$C$10)+$C$11*SUMIFS($F$12:$W$12,$F$4:$W$4,F$4-$C$10-1) -> 0 | G13: =(1-$C$11)*SUMIFS($F$12:$W$12,$F$4:$W$4,G$4-$C$10)+$C$11*SUMIFS($F$12:$W$12,$F$4:$W$4,G$4-$C$10-1) -> 0 | H13: =(1-$C$11)*SUMIFS($F$12:$W$12,$F$4:$W$4,H$4-$C$10)+$C$11*SUMIFS($F$12:$W$12,$F$4:$W$4,H$4-$C$10-1) -> 199609.65 | I13: =(1-$C$11)*SUMIFS($F$12:$W$12,$F$4:$W$4,I$4-$C$10)+$C$11*SUMIFS($F$12:$W$12,$F$4:$W$4,I$4-$C$10-1) -> 507341.2 | J13: =(1-$C$11)*SUMIFS($F$12:$W$12,$F$4:$W$4,J$4-$C$10)+$C$11*SUMIFS($F$12:$W$12,$F$4:$W$4,J$4-$C$10-1) -> 756853.26 | K13: =(1-$C$11)*SUMIFS($F$12:$W$12,$F$4:$W$4,K$4-$C$10)+$C$11*SUMIFS($F$12:$W$12,$F$4:$W$4,K$4-$C$10-1) -> 973844.74 | L13: =(1-$C$11)*SUMIFS($F$12:$W$12,$F$4:$W$4,L$4-$C$10)+$C$11*SUMIFS($F$12:$W$12,$F$4:$W$4,L$4-$C$10-1) -> 1160885.3 | M13: =(1-$C$11)*SUMIFS($F$12:$W$12,$F$4:$W$4,M$4-$C$10)+$C$11*SUMIFS($F$12:$W$12,$F$4:$W$4,M$4-$C$10-1) -> 1247560.3 | ... W13: =(1-$C$11)*SUMIFS($F$12:$W$12,$F$4:$W$4,W$4-$C$10)+$C$11*SUMIFS($F$12:$W$12,$F$4:$W$4,W$4-$C$10-1) -> 1311340.3
A15: ВЫПЛАТЫ
A16: Оплата поставщику (товар + агент + банк) | B16: ₽ | D16: =SUM(F16:W16) -> 7544803.6 | F16: =SUM(F17:F21) -> 526906.8 | G16: =SUM(G17:G21) -> 395180.1 | H16: =SUM(H17:H21) -> 337471.26 | I16: =SUM(I17:I21) -> 444107.16 | J16: =SUM(J17:J21) -> 272235.18 | K16: =SUM(K17:K21) -> 446616.24 | L16: =SUM(L17:L21) -> 395180.1 | M16: =SUM(M17:M21) -> 417761.82 | ... W16: =SUM(W17:W21) -> 395180.1
A17: =""&Допущения!$C$38 -> Органайзер в багажник | B17: ₽ | C17: ='Юнит-экономика'!$C$21 -> 401.4528 | D17: =SUM(F17:W17) -> 1043777.3 | F17: ='Закупки и склад'!F$71*$C17 -> 80290.56 | G17: ='Закупки и склад'!G$71*$C17 -> 80290.56 | H17: ='Закупки и склад'!H$71*$C17 -> 0 | I17: ='Закупки и склад'!I$71*$C17 -> 80290.56 | J17: ='Закупки и склад'!J$71*$C17 -> 80290.56 | K17: ='Закупки и склад'!K$71*$C17 -> 0 | L17: ='Закупки и склад'!L$71*$C17 -> 80290.56 | M17: ='Закупки и склад'!M$71*$C17 -> 80290.56 | ... W17: ='Закупки и склад'!W$71*$C17 -> 80290.56
A18: =""&Допущения!$D$38 -> Автопылесос беспроводной | B18: ₽ | C18: ='Юнит-экономика'!$D$21 -> 727.6332 | D18: =SUM(F18:W18) -> 1637174.7 | F18: ='Закупки и склад'!F$72*$C18 -> 109144.98 | G18: ='Закупки и склад'!G$72*$C18 -> 109144.98 | H18: ='Закупки и склад'!H$72*$C18 -> 0 | I18: ='Закупки и склад'!I$72*$C18 -> 109144.98 | J18: ='Закупки и склад'!J$72*$C18 -> 109144.98 | K18: ='Закупки и склад'!K$72*$C18 -> 109144.98 | L18: ='Закупки и склад'!L$72*$C18 -> 109144.98 | M18: ='Закупки и склад'!M$72*$C18 -> 0 | ... W18: ='Закупки и склад'!W$72*$C18 -> 109144.98
A19: =""&Допущения!$E$38 -> Держатель телефона MagSafe | B19: ₽ | C19: ='Юнит-экономика'!$E$21 -> 275.9988 | D19: =SUM(F19:W19) -> 1324794.2 | F19: ='Закупки и склад'!F$73*$C19 -> 82799.64 | G19: ='Закупки и склад'!G$73*$C19 -> 82799.64 | H19: ='Закупки и склад'!H$73*$C19 -> 82799.64 | I19: ='Закупки и склад'!I$73*$C19 -> 0 | J19: ='Закупки и склад'!J$73*$C19 -> 82799.64 | K19: ='Закупки и склад'!K$73*$C19 -> 82799.64 | L19: ='Закупки и склад'!L$73*$C19 -> 82799.64 | M19: ='Закупки и склад'!M$73*$C19 -> 82799.64 | ... W19: ='Закупки и склад'!W$73*$C19 -> 82799.64
A20: =""&Допущения!$F$38 -> Чехлы на сиденья, комплект | B20: ₽ | C20: ='Юнит-экономика'!$F$21 -> 1317.267 | D20: =SUM(F20:W20) -> 1448993.7 | F20: ='Закупки и склад'!F$74*$C20 -> 131726.7 | G20: ='Закупки и склад'!G$74*$C20 -> 0 | H20: ='Закупки и склад'!H$74*$C20 -> 131726.7 | I20: ='Закупки и склад'!I$74*$C20 -> 131726.7 | J20: ='Закупки и склад'!J$74*$C20 -> 0 | K20: ='Закупки и склад'!K$74*$C20 -> 131726.7 | L20: ='Закупки и склад'!L$74*$C20 -> 0 | M20: ='Закупки и склад'!M$74*$C20 -> 131726.7 | ... W20: ='Закупки и склад'!W$74*$C20 -> 0
A21: =""&Допущения!$G$38 -> Видеорегистратор Wi-Fi | B21: ₽ | C21: ='Юнит-экономика'!$G$21 -> 1229.4492 | D21: =SUM(F21:W21) -> 2090063.6 | F21: ='Закупки и склад'!F$75*$C21 -> 122944.92 | G21: ='Закупки и склад'!G$75*$C21 -> 122944.92 | H21: ='Закупки и склад'!H$75*$C21 -> 122944.92 | I21: ='Закупки и склад'!I$75*$C21 -> 122944.92 | J21: ='Закупки и склад'!J$75*$C21 -> 0 | K21: ='Закупки и склад'!K$75*$C21 -> 122944.92 | L21: ='Закупки и склад'!L$75*$C21 -> 122944.92 | M21: ='Закупки и склад'!M$75*$C21 -> 122944.92 | ... W21: ='Закупки и склад'!W$75*$C21 -> 122944.92
A22: Доставка из Китая | B22: ₽ | D22: =SUM(F22:W22) -> 2101400 | F22: =SUM(F23:F27) -> 0 | G22: =SUM(G23:G27) -> 0 | H22: =SUM(H23:H27) -> 176400 | I22: =SUM(I23:I27) -> 119200 | J22: =SUM(J23:J27) -> 85800 | K22: =SUM(K23:K27) -> 156600 | L22: =SUM(L23:L27) -> 110400 | M22: =SUM(M23:M27) -> 118800 | ... W22: =SUM(W23:W27) -> 176400
A23: =""&Допущения!$C$38 -> Органайзер в багажник | B23: ₽ | C23: ='Юнит-экономика'!$C$13 -> 288 | D23: =SUM(F23:W23) -> 691200 | F23: ='Закупки и склад'!F$16*$C23 -> 0 | G23: ='Закупки и склад'!G$16*$C23 -> 0 | H23: ='Закупки и склад'!H$16*$C23 -> 57600 | I23: ='Закупки и склад'!I$16*$C23 -> 57600 | J23: ='Закупки и склад'!J$16*$C23 -> 0 | K23: ='Закупки и склад'!K$16*$C23 -> 57600 | L23: ='Закупки и склад'!L$16*$C23 -> 57600 | M23: ='Закупки и склад'!M$16*$C23 -> 0 | ... W23: ='Закупки и склад'!W$16*$C23 -> 57600
A24: =""&Допущения!$D$38 -> Автопылесос беспроводной | B24: ₽ | C24: ='Юнит-экономика'!$D$13 -> 220 | D24: =SUM(F24:W24) -> 429000 | F24: ='Закупки и склад'!F$17*$C24 -> 0 | G24: ='Закупки и склад'!G$17*$C24 -> 0 | H24: ='Закупки и склад'!H$17*$C24 -> 33000 | I24: ='Закупки и склад'!I$17*$C24 -> 33000 | J24: ='Закупки и склад'!J$17*$C24 -> 0 | K24: ='Закупки и склад'!K$17*$C24 -> 33000 | L24: ='Закупки и склад'!L$17*$C24 -> 33000 | M24: ='Закупки и склад'!M$17*$C24 -> 33000 | ... W24: ='Закупки и склад'!W$17*$C24 -> 33000
A25: =""&Допущения!$E$38 -> Держатель телефона MagSafe | B25: ₽ | C25: ='Юнит-экономика'!$E$13 -> 66 | D25: =SUM(F25:W25) -> 277200 | F25: ='Закупки и склад'!F$18*$C25 -> 0 | G25: ='Закупки и склад'!G$18*$C25 -> 0 | H25: ='Закупки и склад'!H$18*$C25 -> 19800 | I25: ='Закупки и склад'!I$18*$C25 -> 19800 | J25: ='Закупки и склад'!J$18*$C25 -> 19800 | K25: ='Закупки и склад'!K$18*$C25 -> 0 | L25: ='Закупки и склад'!L$18*$C25 -> 19800 | M25: ='Закупки и склад'!M$18*$C25 -> 19800 | ... W25: ='Закупки и склад'!W$18*$C25 -> 19800
A26: =""&Допущения!$F$38 -> Чехлы на сиденья, комплект | B26: ₽ | C26: ='Юнит-экономика'!$F$13 -> 572 | D26: =SUM(F26:W26) -> 572000 | F26: ='Закупки и склад'!F$19*$C26 -> 0 | G26: ='Закупки и склад'!G$19*$C26 -> 0 | H26: ='Закупки и склад'!H$19*$C26 -> 57200 | I26: ='Закупки и склад'!I$19*$C26 -> 0 | J26: ='Закупки и склад'!J$19*$C26 -> 57200 | K26: ='Закупки и склад'!K$19*$C26 -> 57200 | L26: ='Закупки и склад'!L$19*$C26 -> 0 | M26: ='Закупки и склад'!M$19*$C26 -> 57200 | ... W26: ='Закупки и склад'!W$19*$C26 -> 57200
A27: =""&Допущения!$G$38 -> Видеорегистратор Wi-Fi | B27: ₽ | C27: ='Юнит-экономика'!$G$13 -> 88 | D27: =SUM(F27:W27) -> 132000 | F27: ='Закупки и склад'!F$20*$C27 -> 0 | G27: ='Закупки и склад'!G$20*$C27 -> 0 | H27: ='Закупки и склад'!H$20*$C27 -> 8800 | I27: ='Закупки и склад'!I$20*$C27 -> 8800 | J27: ='Закупки и склад'!J$20*$C27 -> 8800 | K27: ='Закупки и склад'!K$20*$C27 -> 8800 | L27: ='Закупки и склад'!L$20*$C27 -> 0 | M27: ='Закупки и склад'!M$20*$C27 -> 8800 | ... W27: ='Закупки и склад'!W$20*$C27 -> 8800
A28: Пошлина | B28: ₽ | D28: =SUM(F28:W28) -> 433790 | F28: =SUM(F29:F33) -> 0 | G28: =SUM(G29:G33) -> 0 | H28: =SUM(H29:H33) -> 38630 | I28: =SUM(I29:I33) -> 20310 | J28: =SUM(J29:J33) -> 18320 | K28: =SUM(K29:K33) -> 38630 | L28: =SUM(L29:L33) -> 20310 | M28: =SUM(M29:M33) -> 25190 | ... W28: =SUM(W29:W33) -> 38630
A29: =""&Допущения!$C$38 -> Органайзер в багажник | B29: ₽ | C29: ='Юнит-экономика'!$C$15 -> 67.2 | D29: =SUM(F29:W29) -> 161280 | F29: ='Закупки и склад'!F$16*$C29 -> 0 | G29: ='Закупки и склад'!G$16*$C29 -> 0 | H29: ='Закупки и склад'!H$16*$C29 -> 13440 | I29: ='Закупки и склад'!I$16*$C29 -> 13440 | J29: ='Закупки и склад'!J$16*$C29 -> 0 | K29: ='Закупки и склад'!K$16*$C29 -> 13440 | L29: ='Закупки и склад'!L$16*$C29 -> 13440 | M29: ='Закупки и склад'!M$16*$C29 -> 0 | ... W29: ='Закупки и склад'!W$16*$C29 -> 13440
A30: =""&Допущения!$D$38 -> Автопылесос беспроводной | B30: ₽ | C30: ='Юнит-экономика'!$D$15 -> 45.8 | D30: =SUM(F30:W30) -> 89310 | F30: ='Закупки и склад'!F$17*$C30 -> 0 | G30: ='Закупки и склад'!G$17*$C30 -> 0 | H30: ='Закупки и склад'!H$17*$C30 -> 6870 | I30: ='Закупки и склад'!I$17*$C30 -> 6870 | J30: ='Закупки и склад'!J$17*$C30 -> 0 | K30: ='Закупки и склад'!K$17*$C30 -> 6870 | L30: ='Закупки и склад'!L$17*$C30 -> 6870 | M30: ='Закупки и склад'!M$17*$C30 -> 6870 | ... W30: ='Закупки и склад'!W$17*$C30 -> 6870
A31: =""&Допущения!$E$38 -> Держатель телефона MagSafe | B31: ₽ | C31: ='Юнит-экономика'!$E$15 -> 0 | D31: =SUM(F31:W31) -> 0 | F31: ='Закупки и склад'!F$18*$C31 -> 0 | G31: ='Закупки и склад'!G$18*$C31 -> 0 | H31: ='Закупки и склад'!H$18*$C31 -> 0 | I31: ='Закупки и склад'!I$18*$C31 -> 0 | J31: ='Закупки и склад'!J$18*$C31 -> 0 | K31: ='Закупки и склад'!K$18*$C31 -> 0 | L31: ='Закупки и склад'!L$18*$C31 -> 0 | M31: ='Закупки и склад'!M$18*$C31 -> 0 | ... W31: ='Закупки и склад'!W$18*$C31 -> 0
A32: =""&Допущения!$F$38 -> Чехлы на сиденья, комплект | B32: ₽ | C32: ='Юнит-экономика'!$F$15 -> 183.2 | D32: =SUM(F32:W32) -> 183200 | F32: ='Закупки и склад'!F$19*$C32 -> 0 | G32: ='Закупки и склад'!G$19*$C32 -> 0 | H32: ='Закупки и склад'!H$19*$C32 -> 18320 | I32: ='Закупки и склад'!I$19*$C32 -> 0 | J32: ='Закупки и склад'!J$19*$C32 -> 18320 | K32: ='Закупки и склад'!K$19*$C32 -> 18320 | L32: ='Закупки и склад'!L$19*$C32 -> 0 | M32: ='Закупки и склад'!M$19*$C32 -> 18320 | ... W32: ='Закупки и склад'!W$19*$C32 -> 18320
A33: =""&Допущения!$G$38 -> Видеорегистратор Wi-Fi | B33: ₽ | C33: ='Юнит-экономика'!$G$15 -> 0 | D33: =SUM(F33:W33) -> 0 | F33: ='Закупки и склад'!F$20*$C33 -> 0 | G33: ='Закупки и склад'!G$20*$C33 -> 0 | H33: ='Закупки и склад'!H$20*$C33 -> 0 | I33: ='Закупки и склад'!I$20*$C33 -> 0 | J33: ='Закупки и склад'!J$20*$C33 -> 0 | K33: ='Закупки и склад'!K$20*$C33 -> 0 | L33: ='Закупки и склад'!L$20*$C33 -> 0 | M33: ='Закупки и склад'!M$20*$C33 -> 0 | ... W33: ='Закупки и склад'!W$20*$C33 -> 0
A34: НДС на ввоз | B34: ₽ | D34: =SUM(F34:W34) -> 1968293.8 | F34: =SUM(F35:F39) -> 0 | G34: =SUM(G35:G39) -> 0 | H34: =SUM(H35:H39) -> 158186.6 | I34: =SUM(I35:I39) -> 113852.2 | J34: =SUM(J35:J39) -> 93922.4 | K34: =SUM(K35:K39) -> 136406.6 | L34: =SUM(L35:L39) -> 86044.2 | M34: =SUM(M35:M39) -> 125661.8 | ... W34: =SUM(W35:W39) -> 158186.6
A35: =""&Допущения!$C$38 -> Органайзер в багажник | B35: ₽ | C35: ='Юнит-экономика'!$C$16 -> 162.624 | D35: =SUM(F35:W35) -> 390297.6 | F35: ='Закупки и склад'!F$16*$C35 -> 0 | G35: ='Закупки и склад'!G$16*$C35 -> 0 | H35: ='Закупки и склад'!H$16*$C35 -> 32524.8 | I35: ='Закупки и склад'!I$16*$C35 -> 32524.8 | J35: ='Закупки и склад'!J$16*$C35 -> 0 | K35: ='Закупки и склад'!K$16*$C35 -> 32524.8 | L35: ='Закупки и склад'!L$16*$C35 -> 32524.8 | M35: ='Закупки и склад'!M$16*$C35 -> 0 | ... W35: ='Закупки и склад'!W$16*$C35 -> 32524.8
A36: =""&Допущения!$D$38 -> Автопылесос беспроводной | B36: ₽ | C36: ='Юнит-экономика'!$D$16 -> 211.596 | D36: =SUM(F36:W36) -> 412612.2 | F36: ='Закупки и склад'!F$17*$C36 -> 0 | G36: ='Закупки и склад'!G$17*$C36 -> 0 | H36: ='Закупки и склад'!H$17*$C36 -> 31739.4 | I36: ='Закупки и склад'!I$17*$C36 -> 31739.4 | J36: ='Закупки и склад'!J$17*$C36 -> 0 | K36: ='Закупки и склад'!K$17*$C36 -> 31739.4 | L36: ='Закупки и склад'!L$17*$C36 -> 31739.4 | M36: ='Закупки и склад'!M$17*$C36 -> 31739.4 | ... W36: ='Закупки и склад'!W$17*$C36 -> 31739.4
A37: =""&Допущения!$E$38 -> Держатель телефона MagSafe | B37: ₽ | C37: ='Юнит-экономика'!$E$16 -> 72.6 | D37: =SUM(F37:W37) -> 304920 | F37: ='Закупки и склад'!F$18*$C37 -> 0 | G37: ='Закупки и склад'!G$18*$C37 -> 0 | H37: ='Закупки и склад'!H$18*$C37 -> 21780 | I37: ='Закупки и склад'!I$18*$C37 -> 21780 | J37: ='Закупки и склад'!J$18*$C37 -> 21780 | K37: ='Закупки и склад'!K$18*$C37 -> 0 | L37: ='Закупки и склад'!L$18*$C37 -> 21780 | M37: ='Закупки и склад'!M$18*$C37 -> 21780 | ... W37: ='Закупки и склад'!W$18*$C37 -> 21780
A38: =""&Допущения!$F$38 -> Чехлы на сиденья, комплект | B38: ₽ | C38: ='Юнит-экономика'!$F$16 -> 443.344 | D38: =SUM(F38:W38) -> 443344 | F38: ='Закупки и склад'!F$19*$C38 -> 0 | G38: ='Закупки и склад'!G$19*$C38 -> 0 | H38: ='Закупки и склад'!H$19*$C38 -> 44334.4 | I38: ='Закупки и склад'!I$19*$C38 -> 0 | J38: ='Закупки и склад'!J$19*$C38 -> 44334.4 | K38: ='Закупки и склад'!K$19*$C38 -> 44334.4 | L38: ='Закупки и склад'!L$19*$C38 -> 0 | M38: ='Закупки и склад'!M$19*$C38 -> 44334.4 | ... W38: ='Закупки и склад'!W$19*$C38 -> 44334.4
A39: =""&Допущения!$G$38 -> Видеорегистратор Wi-Fi | B39: ₽ | C39: ='Юнит-экономика'!$G$16 -> 278.08 | D39: =SUM(F39:W39) -> 417120 | F39: ='Закупки и склад'!F$20*$C39 -> 0 | G39: ='Закупки и склад'!G$20*$C39 -> 0 | H39: ='Закупки и склад'!H$20*$C39 -> 27808 | I39: ='Закупки и склад'!I$20*$C39 -> 27808 | J39: ='Закупки и склад'!J$20*$C39 -> 27808 | K39: ='Закупки и склад'!K$20*$C39 -> 27808 | L39: ='Закупки и склад'!L$20*$C39 -> 0 | M39: ='Закупки и склад'!M$20*$C39 -> 27808 | ... W39: ='Закупки и склад'!W$20*$C39 -> 27808
A40: Таможенное оформление | B40: ₽ | D40: =SUM(F40:W40) -> 512000 | F40: =SUM(F41:F45) -> 0 | G40: =SUM(G41:G45) -> 0 | H40: =SUM(H41:H45) -> 40000 | I40: =SUM(I41:I45) -> 32000 | J40: =SUM(J41:J45) -> 24000 | K40: =SUM(K41:K45) -> 32000 | L40: =SUM(L41:L45) -> 24000 | M40: =SUM(M41:M45) -> 32000 | ... W40: =SUM(W41:W45) -> 40000
A41: =""&Допущения!$C$38 -> Органайзер в багажник | B41: ₽ | C41: ='Юнит-экономика'!$C$17 -> 40 | D41: =SUM(F41:W41) -> 96000 | F41: ='Закупки и склад'!F$16*$C41 -> 0 | G41: ='Закупки и склад'!G$16*$C41 -> 0 | H41: ='Закупки и склад'!H$16*$C41 -> 8000 | I41: ='Закупки и склад'!I$16*$C41 -> 8000 | J41: ='Закупки и склад'!J$16*$C41 -> 0 | K41: ='Закупки и склад'!K$16*$C41 -> 8000 | L41: ='Закупки и склад'!L$16*$C41 -> 8000 | M41: ='Закупки и склад'!M$16*$C41 -> 0 | ... W41: ='Закупки и склад'!W$16*$C41 -> 8000
A42: =""&Допущения!$D$38 -> Автопылесос беспроводной | B42: ₽ | C42: ='Юнит-экономика'!$D$17 -> 53.333333 | D42: =SUM(F42:W42) -> 104000 | F42: ='Закупки и склад'!F$17*$C42 -> 0 | G42: ='Закупки и склад'!G$17*$C42 -> 0 | H42: ='Закупки и склад'!H$17*$C42 -> 8000 | I42: ='Закупки и склад'!I$17*$C42 -> 8000 | J42: ='Закупки и склад'!J$17*$C42 -> 0 | K42: ='Закупки и склад'!K$17*$C42 -> 8000 | L42: ='Закупки и склад'!L$17*$C42 -> 8000 | M42: ='Закупки и склад'!M$17*$C42 -> 8000 | ... W42: ='Закупки и склад'!W$17*$C42 -> 8000
A43: =""&Допущения!$E$38 -> Держатель телефона MagSafe | B43: ₽ | C43: ='Юнит-экономика'!$E$17 -> 26.666667 | D43: =SUM(F43:W43) -> 112000 | F43: ='Закупки и склад'!F$18*$C43 -> 0 | G43: ='Закупки и склад'!G$18*$C43 -> 0 | H43: ='Закупки и склад'!H$18*$C43 -> 8000 | I43: ='Закупки и склад'!I$18*$C43 -> 8000 | J43: ='Закупки и склад'!J$18*$C43 -> 8000 | K43: ='Закупки и склад'!K$18*$C43 -> 0 | L43: ='Закупки и склад'!L$18*$C43 -> 8000 | M43: ='Закупки и склад'!M$18*$C43 -> 8000 | ... W43: ='Закупки и склад'!W$18*$C43 -> 8000
A44: =""&Допущения!$F$38 -> Чехлы на сиденья, комплект | B44: ₽ | C44: ='Юнит-экономика'!$F$17 -> 80 | D44: =SUM(F44:W44) -> 80000 | F44: ='Закупки и склад'!F$19*$C44 -> 0 | G44: ='Закупки и склад'!G$19*$C44 -> 0 | H44: ='Закупки и склад'!H$19*$C44 -> 8000 | I44: ='Закупки и склад'!I$19*$C44 -> 0 | J44: ='Закупки и склад'!J$19*$C44 -> 8000 | K44: ='Закупки и склад'!K$19*$C44 -> 8000 | L44: ='Закупки и склад'!L$19*$C44 -> 0 | M44: ='Закупки и склад'!M$19*$C44 -> 8000 | ... W44: ='Закупки и склад'!W$19*$C44 -> 8000
A45: =""&Допущения!$G$38 -> Видеорегистратор Wi-Fi | B45: ₽ | C45: ='Юнит-экономика'!$G$17 -> 80 | D45: =SUM(F45:W45) -> 120000 | F45: ='Закупки и склад'!F$20*$C45 -> 0 | G45: ='Закупки и склад'!G$20*$C45 -> 0 | H45: ='Закупки и склад'!H$20*$C45 -> 8000 | I45: ='Закупки и склад'!I$20*$C45 -> 8000 | J45: ='Закупки и склад'!J$20*$C45 -> 8000 | K45: ='Закупки и склад'!K$20*$C45 -> 8000 | L45: ='Закупки и склад'!L$20*$C45 -> 0 | M45: ='Закупки и склад'!M$20*$C45 -> 8000 | ... W45: ='Закупки и склад'!W$20*$C45 -> 8000
A46: Упаковка, маркировка, доставка до склада МП | B46: ₽ | D46: =SUM(F46:W46) -> 568250 | F46: =SUM(F47:F51) -> 0 | G46: =SUM(G47:G51) -> 0 | H46: =SUM(H47:H51) -> 46000 | I46: =SUM(I47:I51) -> 35000 | J46: =SUM(J47:J51) -> 24250 | K46: =SUM(K47:K51) -> 36250 | L46: =SUM(L47:L51) -> 31500 | M46: =SUM(M47:M51) -> 32500 | ... W46: =SUM(W47:W51) -> 46000
A47: =""&Допущения!$C$38 -> Органайзер в багажник | B47: ₽ | C47: ='Юнит-экономика'!$C$18+'Юнит-экономика'!$C$19 -> 67.5 | D47: =SUM(F47:W47) -> 162000 | F47: ='Закупки и склад'!F$16*$C47 -> 0 | G47: ='Закупки и склад'!G$16*$C47 -> 0 | H47: ='Закупки и склад'!H$16*$C47 -> 13500 | I47: ='Закупки и склад'!I$16*$C47 -> 13500 | J47: ='Закупки и склад'!J$16*$C47 -> 0 | K47: ='Закупки и склад'!K$16*$C47 -> 13500 | L47: ='Закупки и склад'!L$16*$C47 -> 13500 | M47: ='Закупки и склад'!M$16*$C47 -> 0 | ... W47: ='Закупки и склад'!W$16*$C47 -> 13500
A48: =""&Допущения!$D$38 -> Автопылесос беспроводной | B48: ₽ | C48: ='Юнит-экономика'!$D$18+'Юнит-экономика'!$D$19 -> 55 | D48: =SUM(F48:W48) -> 107250 | F48: ='Закупки и склад'!F$17*$C48 -> 0 | G48: ='Закупки и склад'!G$17*$C48 -> 0 | H48: ='Закупки и склад'!H$17*$C48 -> 8250 | I48: ='Закупки и склад'!I$17*$C48 -> 8250 | J48: ='Закупки и склад'!J$17*$C48 -> 0 | K48: ='Закупки и склад'!K$17*$C48 -> 8250 | L48: ='Закупки и склад'!L$17*$C48 -> 8250 | M48: ='Закупки и склад'!M$17*$C48 -> 8250 | ... W48: ='Закупки и склад'!W$17*$C48 -> 8250
A49: =""&Допущения!$E$38 -> Держатель телефона MagSafe | B49: ₽ | C49: ='Юнит-экономика'!$E$18+'Юнит-экономика'!$E$19 -> 32.5 | D49: =SUM(F49:W49) -> 136500 | F49: ='Закупки и склад'!F$18*$C49 -> 0 | G49: ='Закупки и склад'!G$18*$C49 -> 0 | H49: ='Закупки и склад'!H$18*$C49 -> 9750 | I49: ='Закупки и склад'!I$18*$C49 -> 9750 | J49: ='Закупки и склад'!J$18*$C49 -> 9750 | K49: ='Закупки и склад'!K$18*$C49 -> 0 | L49: ='Закупки и склад'!L$18*$C49 -> 9750 | M49: ='Закупки и склад'!M$18*$C49 -> 9750 | ... W49: ='Закупки и склад'!W$18*$C49 -> 9750
A50: =""&Допущения!$F$38 -> Чехлы на сиденья, комплект | B50: ₽ | C50: ='Юнит-экономика'!$F$18+'Юнит-экономика'!$F$19 -> 110 | D50: =SUM(F50:W50) -> 110000 | F50: ='Закупки и склад'!F$19*$C50 -> 0 | G50: ='Закупки и склад'!G$19*$C50 -> 0 | H50: ='Закупки и склад'!H$19*$C50 -> 11000 | I50: ='Закупки и склад'!I$19*$C50 -> 0 | J50: ='Закупки и склад'!J$19*$C50 -> 11000 | K50: ='Закупки и склад'!K$19*$C50 -> 11000 | L50: ='Закупки и склад'!L$19*$C50 -> 0 | M50: ='Закупки и склад'!M$19*$C50 -> 11000 | ... W50: ='Закупки и склад'!W$19*$C50 -> 11000
A51: =""&Допущения!$G$38 -> Видеорегистратор Wi-Fi | B51: ₽ | C51: ='Юнит-экономика'!$G$18+'Юнит-экономика'!$G$19 -> 35 | D51: =SUM(F51:W51) -> 52500 | F51: ='Закупки и склад'!F$20*$C51 -> 0 | G51: ='Закупки и склад'!G$20*$C51 -> 0 | H51: ='Закупки и склад'!H$20*$C51 -> 3500 | I51: ='Закупки и склад'!I$20*$C51 -> 3500 | J51: ='Закупки и склад'!J$20*$C51 -> 3500 | K51: ='Закупки и склад'!K$20*$C51 -> 3500 | L51: ='Закупки и склад'!L$20*$C51 -> 0 | M51: ='Закупки и склад'!M$20*$C51 -> 3500 | ... W51: ='Закупки и склад'!W$20*$C51 -> 3500
A52: Сертификация (в месяц первого заказа) | B52: ₽ | D52: =SUM(F52:W52) -> 175000 | F52: =SUM(F53:F57) -> 175000 | G52: =SUM(G53:G57) -> 0 | H52: =SUM(H53:H57) -> 0 | I52: =SUM(I53:I57) -> 0 | J52: =SUM(J53:J57) -> 0 | K52: =SUM(K53:K57) -> 0 | L52: =SUM(L53:L57) -> 0 | M52: =SUM(M53:M57) -> 0 | ... W52: =SUM(W53:W57) -> 0
A53: =""&Допущения!$C$38 -> Органайзер в багажник | B53: ₽ | C53: =Допущения!$C$48 -> 20000 | D53: =SUM(F53:W53) -> 20000 | F53: =IF(AND('Закупки и склад'!F71>0,SUM('Закупки и склад'!$E71:E71)=0),$C53,0) -> 20000 | G53: =IF(AND('Закупки и склад'!G71>0,SUM('Закупки и склад'!$E71:F71)=0),$C53,0) -> 0 | H53: =IF(AND('Закупки и склад'!H71>0,SUM('Закупки и склад'!$E71:G71)=0),$C53,0) -> 0 | I53: =IF(AND('Закупки и склад'!I71>0,SUM('Закупки и склад'!$E71:H71)=0),$C53,0) -> 0 | J53: =IF(AND('Закупки и склад'!J71>0,SUM('Закупки и склад'!$E71:I71)=0),$C53,0) -> 0 | K53: =IF(AND('Закупки и склад'!K71>0,SUM('Закупки и склад'!$E71:J71)=0),$C53,0) -> 0 | L53: =IF(AND('Закупки и склад'!L71>0,SUM('Закупки и склад'!$E71:K71)=0),$C53,0) -> 0 | M53: =IF(AND('Закупки и склад'!M71>0,SUM('Закупки и склад'!$E71:L71)=0),$C53,0) -> 0 | ... W53: =IF(AND('Закупки и склад'!W71>0,SUM('Закупки и склад'!$E71:V71)=0),$C53,0) -> 0
A54: =""&Допущения!$D$38 -> Автопылесос беспроводной | B54: ₽ | C54: =Допущения!$D$48 -> 45000 | D54: =SUM(F54:W54) -> 45000 | F54: =IF(AND('Закупки и склад'!F72>0,SUM('Закупки и склад'!$E72:E72)=0),$C54,0) -> 45000 | G54: =IF(AND('Закупки и склад'!G72>0,SUM('Закупки и склад'!$E72:F72)=0),$C54,0) -> 0 | H54: =IF(AND('Закупки и склад'!H72>0,SUM('Закупки и склад'!$E72:G72)=0),$C54,0) -> 0 | I54: =IF(AND('Закупки и склад'!I72>0,SUM('Закупки и склад'!$E72:H72)=0),$C54,0) -> 0 | J54: =IF(AND('Закупки и склад'!J72>0,SUM('Закупки и склад'!$E72:I72)=0),$C54,0) -> 0 | K54: =IF(AND('Закупки и склад'!K72>0,SUM('Закупки и склад'!$E72:J72)=0),$C54,0) -> 0 | L54: =IF(AND('Закупки и склад'!L72>0,SUM('Закупки и склад'!$E72:K72)=0),$C54,0) -> 0 | M54: =IF(AND('Закупки и склад'!M72>0,SUM('Закупки и склад'!$E72:L72)=0),$C54,0) -> 0 | ... W54: =IF(AND('Закупки и склад'!W72>0,SUM('Закупки и склад'!$E72:V72)=0),$C54,0) -> 0
A55: =""&Допущения!$E$38 -> Держатель телефона MagSafe | B55: ₽ | C55: =Допущения!$E$48 -> 40000 | D55: =SUM(F55:W55) -> 40000 | F55: =IF(AND('Закупки и склад'!F73>0,SUM('Закупки и склад'!$E73:E73)=0),$C55,0) -> 40000 | G55: =IF(AND('Закупки и склад'!G73>0,SUM('Закупки и склад'!$E73:F73)=0),$C55,0) -> 0 | H55: =IF(AND('Закупки и склад'!H73>0,SUM('Закупки и склад'!$E73:G73)=0),$C55,0) -> 0 | I55: =IF(AND('Закупки и склад'!I73>0,SUM('Закупки и склад'!$E73:H73)=0),$C55,0) -> 0 | J55: =IF(AND('Закупки и склад'!J73>0,SUM('Закупки и склад'!$E73:I73)=0),$C55,0) -> 0 | K55: =IF(AND('Закупки и склад'!K73>0,SUM('Закупки и склад'!$E73:J73)=0),$C55,0) -> 0 | L55: =IF(AND('Закупки и склад'!L73>0,SUM('Закупки и склад'!$E73:K73)=0),$C55,0) -> 0 | M55: =IF(AND('Закупки и склад'!M73>0,SUM('Закупки и склад'!$E73:L73)=0),$C55,0) -> 0 | ... W55: =IF(AND('Закупки и склад'!W73>0,SUM('Закупки и склад'!$E73:V73)=0),$C55,0) -> 0
A56: =""&Допущения!$F$38 -> Чехлы на сиденья, комплект | B56: ₽ | C56: =Допущения!$F$48 -> 20000 | D56: =SUM(F56:W56) -> 20000 | F56: =IF(AND('Закупки и склад'!F74>0,SUM('Закупки и склад'!$E74:E74)=0),$C56,0) -> 20000 | G56: =IF(AND('Закупки и склад'!G74>0,SUM('Закупки и склад'!$E74:F74)=0),$C56,0) -> 0 | H56: =IF(AND('Закупки и склад'!H74>0,SUM('Закупки и склад'!$E74:G74)=0),$C56,0) -> 0 | I56: =IF(AND('Закупки и склад'!I74>0,SUM('Закупки и склад'!$E74:H74)=0),$C56,0) -> 0 | J56: =IF(AND('Закупки и склад'!J74>0,SUM('Закупки и склад'!$E74:I74)=0),$C56,0) -> 0 | K56: =IF(AND('Закупки и склад'!K74>0,SUM('Закупки и склад'!$E74:J74)=0),$C56,0) -> 0 | L56: =IF(AND('Закупки и склад'!L74>0,SUM('Закупки и склад'!$E74:K74)=0),$C56,0) -> 0 | M56: =IF(AND('Закупки и склад'!M74>0,SUM('Закупки и склад'!$E74:L74)=0),$C56,0) -> 0 | ... W56: =IF(AND('Закупки и склад'!W74>0,SUM('Закупки и склад'!$E74:V74)=0),$C56,0) -> 0
A57: =""&Допущения!$G$38 -> Видеорегистратор Wi-Fi | B57: ₽ | C57: =Допущения!$G$48 -> 50000 | D57: =SUM(F57:W57) -> 50000 | F57: =IF(AND('Закупки и склад'!F75>0,SUM('Закупки и склад'!$E75:E75)=0),$C57,0) -> 50000 | G57: =IF(AND('Закупки и склад'!G75>0,SUM('Закупки и склад'!$E75:F75)=0),$C57,0) -> 0 | H57: =IF(AND('Закупки и склад'!H75>0,SUM('Закупки и склад'!$E75:G75)=0),$C57,0) -> 0 | I57: =IF(AND('Закупки и склад'!I75>0,SUM('Закупки и склад'!$E75:H75)=0),$C57,0) -> 0 | J57: =IF(AND('Закупки и склад'!J75>0,SUM('Закупки и склад'!$E75:I75)=0),$C57,0) -> 0 | K57: =IF(AND('Закупки и склад'!K75>0,SUM('Закупки и склад'!$E75:J75)=0),$C57,0) -> 0 | L57: =IF(AND('Закупки и склад'!L75>0,SUM('Закупки и склад'!$E75:K75)=0),$C57,0) -> 0 | M57: =IF(AND('Закупки и склад'!M75>0,SUM('Закупки и склад'!$E75:L75)=0),$C57,0) -> 0 | ... W57: =IF(AND('Закупки и склад'!W75>0,SUM('Закупки и склад'!$E75:V75)=0),$C57,0) -> 0
A58: Реклама | B58: ₽ | D58: =SUM(F58:W58) -> 1952397.6 | F58: =ОПиУ!F35 -> 0 | G58: =ОПиУ!G35 -> 0 | H58: =ОПиУ!H35 -> 39031.2 | I58: =ОПиУ!I35 -> 65052 | J58: =ОПиУ!J35 -> 91072.8 | K58: =ОПиУ!K35 -> 110728 | L58: =ОПиУ!L35 -> 130104 | M58: =ОПиУ!M35 -> 130104 | ... W58: =ОПиУ!W35 -> 136748.8
A59: Постоянные расходы | B59: ₽ | D59: =SUM(F59:W59) -> 900000 | F59: =ОПиУ!F36 -> 50000 | G59: =ОПиУ!G36 -> 50000 | H59: =ОПиУ!H36 -> 50000 | I59: =ОПиУ!I36 -> 50000 | J59: =ОПиУ!J36 -> 50000 | K59: =ОПиУ!K36 -> 50000 | L59: =ОПиУ!L36 -> 50000 | M59: =ОПиУ!M36 -> 50000 | ... W59: =ОПиУ!W36 -> 50000
A60: Стартовые расходы | B60: ₽ | D60: =SUM(F60:W60) -> 60000 | F60: =ОПиУ!F37 -> 60000 | G60: =ОПиУ!G37 -> 0 | H60: =ОПиУ!H37 -> 0 | I60: =ОПиУ!I37 -> 0 | J60: =ОПиУ!J37 -> 0 | K60: =ОПиУ!K37 -> 0 | L60: =ОПиУ!L37 -> 0 | M60: =ОПиУ!M37 -> 0 | ... W60: =ОПиУ!W37 -> 0
A61: Налог (уплата: УСН — поквартально, НПД — ежемесячно) | B61: ₽ | D61: =SUM(F61:W61) -> 1361736.6 | F61: =IF(Налог_номер=3,SUMIFS(ОПиУ!$F$45:$W$45,ОПиУ!$F$4:$W$4,F$4-1),IF(MOD(MONTH(F$5),3)=1,SUMIFS(ОПиУ!$F$45:$W$45,ОПиУ!$F$4:$W$4,">="&(F$4-3),ОПиУ!$F$4:$W$4,"<"&F$4),0)) -> 0 | G61: =IF(Налог_номер=3,SUMIFS(ОПиУ!$F$45:$W$45,ОПиУ!$F$4:$W$4,G$4-1),IF(MOD(MONTH(G$5),3)=1,SUMIFS(ОПиУ!$F$45:$W$45,ОПиУ!$F$4:$W$4,">="&(G$4-3),ОПиУ!$F$4:$W$4,"<"&G$4),0)) -> 0 | H61: =IF(Налог_номер=3,SUMIFS(ОПиУ!$F$45:$W$45,ОПиУ!$F$4:$W$4,H$4-1),IF(MOD(MONTH(H$5),3)=1,SUMIFS(ОПиУ!$F$45:$W$45,ОПиУ!$F$4:$W$4,">="&(H$4-3),ОПиУ!$F$4:$W$4,"<"&H$4),0)) -> 0 | I61: =IF(Налог_номер=3,SUMIFS(ОПиУ!$F$45:$W$45,ОПиУ!$F$4:$W$4,I$4-1),IF(MOD(MONTH(I$5),3)=1,SUMIFS(ОПиУ!$F$45:$W$45,ОПиУ!$F$4:$W$4,">="&(I$4-3),ОПиУ!$F$4:$W$4,"<"&I$4),0)) -> 0 | J61: =IF(Налог_номер=3,SUMIFS(ОПиУ!$F$45:$W$45,ОПиУ!$F$4:$W$4,J$4-1),IF(MOD(MONTH(J$5),3)=1,SUMIFS(ОПиУ!$F$45:$W$45,ОПиУ!$F$4:$W$4,">="&(J$4-3),ОПиУ!$F$4:$W$4,"<"&J$4),0)) -> 0 | K61: =IF(Налог_номер=3,SUMIFS(ОПиУ!$F$45:$W$45,ОПиУ!$F$4:$W$4,K$4-1),IF(MOD(MONTH(K$5),3)=1,SUMIFS(ОПиУ!$F$45:$W$45,ОПиУ!$F$4:$W$4,">="&(K$4-3),ОПиУ!$F$4:$W$4,"<"&K$4),0)) -> 146367 | L61: =IF(Налог_номер=3,SUMIFS(ОПиУ!$F$45:$W$45,ОПиУ!$F$4:$W$4,L$4-1),IF(MOD(MONTH(L$5),3)=1,SUMIFS(ОПиУ!$F$45:$W$45,ОПиУ!$F$4:$W$4,">="&(L$4-3),ОПиУ!$F$4:$W$4,"<"&L$4),0)) -> 0 | M61: =IF(Налог_номер=3,SUMIFS(ОПиУ!$F$45:$W$45,ОПиУ!$F$4:$W$4,M$4-1),IF(MOD(MONTH(M$5),3)=1,SUMIFS(ОПиУ!$F$45:$W$45,ОПиУ!$F$4:$W$4,">="&(M$4-3),ОПиУ!$F$4:$W$4,"<"&M$4),0)) -> 0 | ... W61: =IF(Налог_номер=3,SUMIFS(ОПиУ!$F$45:$W$45,ОПиУ!$F$4:$W$4,W$4-1),IF(MOD(MONTH(W$5),3)=1,SUMIFS(ОПиУ!$F$45:$W$45,ОПиУ!$F$4:$W$4,">="&(W$4-3),ОПиУ!$F$4:$W$4,"<"&W$4),0)) -> 287959.8
A62: Итого выплаты | B62: ₽ | D62: =SUM(F62:W62) -> 17577672 | F62: =F16+F22+F28+F34+F40+F46+F52+F58+F59+F60+F61 -> 811906.8 | G62: =G16+G22+G28+G34+G40+G46+G52+G58+G59+G60+G61 -> 445180.1 | H62: =H16+H22+H28+H34+H40+H46+H52+H58+H59+H60+H61 -> 885719.06 | I62: =I16+I22+I28+I34+I40+I46+I52+I58+I59+I60+I61 -> 879521.36 | J62: =J16+J22+J28+J34+J40+J46+J52+J58+J59+J60+J61 -> 659600.38 | K62: =K16+K22+K28+K34+K40+K46+K52+K58+K59+K60+K61 -> 1153597.8 | L62: =L16+L22+L28+L34+L40+L46+L52+L58+L59+L60+L61 -> 847538.3 | M62: =M16+M22+M28+M34+M40+M46+M52+M58+M59+M60+M61 -> 932017.62 | ... W62: =W16+W22+W28+W34+W40+W46+W52+W58+W59+W60+W61 -> 1329105.3
A64: Чистый денежный поток за месяц | B64: ₽ | D64: =SUM(F64:W64) -> 532185.98 | F64: =F13-F62 -> -811906.8 | G64: =G13-G62 -> -445180.1 | H64: =H13-H62 -> -686109.41 | I64: =I13-I62 -> -372180.16 | J64: =J13-J62 -> 97252.881 | K64: =K13-K62 -> -179753.1 | L64: =L13-L62 -> 313347.03 | M64: =M13-M62 -> 315542.7 | ... W64: =W13-W62 -> -17765.043
A65: Остаток денег на конец месяца | B65: ₽ | E65: =Капитал_старт -> 2000000 | F65: =E65+F64 -> 1188093.2 | G65: =F65+G64 -> 742913.1 | H65: =G65+H64 -> 56803.691 | I65: =H65+I64 -> -315376.47 | J65: =I65+J64 -> -218123.59 | K65: =J65+K64 -> -397876.69 | L65: =K65+L64 -> -84529.663 | M65: =L65+M64 -> 231013.04 | ... W65: =V65+W64 -> 2532186
A66: Кассовый разрыв: не хватает денег | B66: ₽ | C66: макс. → | D66: =MAX(F66:W66) -> 397876.69 | F66: =MAX(0,-F65) -> 0 | G66: =MAX(0,-G65) -> 0 | H66: =MAX(0,-H65) -> 0 | I66: =MAX(0,-I65) -> 315376.47 | J66: =MAX(0,-J65) -> 218123.59 | K66: =MAX(0,-K65) -> 397876.69 | L66: =MAX(0,-L65) -> 84529.663 | M66: =MAX(0,-M65) -> 0 | ... W66: =MAX(0,-W65) -> 0
A67: Разрыв в этом месяце? (служебная) | F67: =F65<0 -> FALSE | G67: =G65<0 -> FALSE | H67: =H65<0 -> FALSE | I67: =I65<0 -> TRUE | J67: =J65<0 -> TRUE | K67: =K65<0 -> TRUE | L67: =L65<0 -> TRUE | M67: =M65<0 -> FALSE | ... W67: =W65<0 -> FALSE
A68: Накопленный денежный поток (без стартового капитала) | B68: ₽ | F68: =E68+F64 -> -811906.8 | G68: =F68+G64 -> -1257086.9 | H68: =G68+H64 -> -1943196.3 | I68: =H68+I64 -> -2315376.5 | J68: =I68+J64 -> -2218123.6 | K68: =J68+K64 -> -2397876.7 | L68: =K68+L64 -> -2084529.7 | M68: =L68+M64 -> -1768987 | ... W68: =V68+W64 -> 532185.98
A69: Минимум накопленного потока до конца (служебная) | B69: ₽ | F69: =MIN(F68:$W68) -> -2397876.7 | G69: =MIN(G68:$W68) -> -2397876.7 | H69: =MIN(H68:$W68) -> -2397876.7 | I69: =MIN(I68:$W68) -> -2397876.7 | J69: =MIN(J68:$W68) -> -2397876.7 | K69: =MIN(K68:$W68) -> -2397876.7 | L69: =MIN(L68:$W68) -> -2084529.7 | M69: =MIN(M68:$W68) -> -1772866.1 | ... W69: =MIN(W68:$W68) -> 532185.98
A70: Вложения окупились и больше не уходят в минус? (служебная) | F70: =F69>=0 -> FALSE | G70: =G69>=0 -> FALSE | H70: =H69>=0 -> FALSE | I70: =I69>=0 -> FALSE | J70: =J69>=0 -> FALSE | K70: =K69>=0 -> FALSE | L70: =L69>=0 -> FALSE | M70: =M69>=0 -> FALSE | ... W70: =W69>=0 -> TRUE
A71: Для графика: остаток ≥ 0 (служебная) | B71: ₽ | F71: =MAX(F65,0) -> 1188093.2 | G71: =MAX(G65,0) -> 742913.1 | H71: =MAX(H65,0) -> 56803.691 | I71: =MAX(I65,0) -> 0 | J71: =MAX(J65,0) -> 0 | K71: =MAX(K65,0) -> 0 | L71: =MAX(L65,0) -> 0 | M71: =MAX(M65,0) -> 231013.04 | ... W71: =MAX(W65,0) -> 2532186
A72: Для графика: остаток < 0 (служебная) | B72: ₽ | F72: =MIN(F65,0) -> 0 | G72: =MIN(G65,0) -> 0 | H72: =MIN(H65,0) -> 0 | I72: =MIN(I65,0) -> -315376.47 | J72: =MIN(J65,0) -> -218123.59 | K72: =MIN(K65,0) -> -397876.69 | L72: =MIN(L65,0) -> -84529.663 | M72: =MIN(M65,0) -> 0 | ... W72: =MIN(W65,0) -> 0
A74: Итоги на конец периода и контроль баланса модели
A75: Деньги на счёте | B75: ₽ | D75: =W65 -> 2532186
A76: Товар на складе маркетплейса (по себестоимости) | B76: ₽ | D76: ='Закупки и склад'!W46 -> 1169196
A77: Товар в пути (уже оплачен поставщику) | B77: ₽ | D77: =SUMPRODUCT('Закупки и склад'!W49:W53,'Закупки и склад'!$C49:$C53)+W16 -> 841796.34
A78: Маркетплейс ещё должен выплатить | B78: ₽ | D78: =D12-D13 -> 611958.79
A79: Налог начислен, но ещё не уплачен | B79: ₽ | D79: =ОПиУ!D45-D61 -> 102561.6
A80: Капитал на конец периода (деньги + товар + дебиторка − налог) | B80: ₽ | D80: =D75+D76+D77+D78-D79 -> 5052575.5
A81: Начальный запас по себестоимости | B81: ₽ | D81: =SUMPRODUCT('Закупки и склад'!E40:E44,'Закупки и склад'!$C40:$C44) -> 0
A82: Стартовый капитал + начальный запас + чистая прибыль | B82: ₽ | D82: =Капитал_старт+D81+ОПиУ!D46 -> 5052575.5
A83: Разница (должна быть 0) | B83: ₽ | D83: =D80-D82 -> 0
A84: Контроль баланса | D84: =IF(ROUND(D83,2)=0,"OK","Ошибка") -> OK

Sheet ОПиУ
A1: ОПиУ — отчёт о прибылях и убытках по месяцам (метод начисления)
A2: Выручка и себестоимость — по месяцу выкупа. Налог УСН 15 % считается нарастающим итогом с начала календарного года.
A3: ДЕМО-ДАННЫЕ: все цифры — пример. Ставки пошлин, НДС, налогов и тарифы маркетплейса уточните под свой товар.
A4: Месяц № | F4: =COLUMN()-COLUMN($E$4) -> 1 | G4: =COLUMN()-COLUMN($E$4) -> 2 | H4: =COLUMN()-COLUMN($E$4) -> 3 | I4: =COLUMN()-COLUMN($E$4) -> 4 | J4: =COLUMN()-COLUMN($E$4) -> 5 | K4: =COLUMN()-COLUMN($E$4) -> 6 | L4: =COLUMN()-COLUMN($E$4) -> 7 | M4: =COLUMN()-COLUMN($E$4) -> 8 | ... W4: =COLUMN()-COLUMN($E$4) -> 18
A5: Показатель | B5: Ед. | C5: Параметр | D5: Итого | E5: Старт | F5: =EDATE(Дата_начала,F$4-1) -> 46327 | G5: =EDATE(Дата_начала,G$4-1) -> 46357 | H5: =EDATE(Дата_начала,H$4-1) -> 46388 | I5: =EDATE(Дата_начала,I$4-1) -> 46419 | J5: =EDATE(Дата_начала,J$4-1) -> 46447 | K5: =EDATE(Дата_начала,K$4-1) -> 46478 | L5: =EDATE(Дата_начала,L$4-1) -> 46508 | M5: =EDATE(Дата_начала,M$4-1) -> 46539 | ... W5: =EDATE(Дата_начала,W$4-1) -> 46844
A6: Год (служебная) | F6: =YEAR(F$5) -> 2026 | G6: =YEAR(G$5) -> 2026 | H6: =YEAR(H$5) -> 2027 | I6: =YEAR(I$5) -> 2027 | J6: =YEAR(J$5) -> 2027 | K6: =YEAR(K$5) -> 2027 | L6: =YEAR(L$5) -> 2027 | M6: =YEAR(M$5) -> 2027 | ... W6: =YEAR(W$5) -> 2028
A8: Выручка | B8: ₽ | D8: =SUM(F8:W8) -> 24404970 | F8: =SUM(F9:F13) -> 0 | G8: =SUM(G9:G13) -> 0 | H8: =SUM(H9:H13) -> 487890 | I8: =SUM(I9:I13) -> 813150 | J8: =SUM(J9:J13) -> 1138410 | K8: =SUM(K9:K13) -> 1384100 | L8: =SUM(L9:L13) -> 1626300 | M8: =SUM(M9:M13) -> 1626300 | ... W8: =SUM(W9:W13) -> 1709360
A9: =""&Допущения!$C$38 -> Органайзер в багажник | B9: ₽ | C9: ='Юнит-экономика'!$C$6 -> 2490 | D9: =SUM(F9:W9) -> 5229000 | F9: ='Закупки и склад'!F$24*$C9 -> 0 | G9: ='Закупки и склад'!G$24*$C9 -> 0 | H9: ='Закупки и склад'!H$24*$C9 -> 104580 | I9: ='Закупки и склад'!I$24*$C9 -> 174300 | J9: ='Закупки и склад'!J$24*$C9 -> 244020 | K9: ='Закупки и склад'!K$24*$C9 -> 296310 | L9: ='Закупки и склад'!L$24*$C9 -> 348600 | M9: ='Закупки и склад'!M$24*$C9 -> 348600 | ... W9: ='Закупки и склад'!W$24*$C9 -> 366030
A10: =""&Допущения!$D$38 -> Автопылесос беспроводной | B10: ₽ | C10: ='Юнит-экономика'!$D$6 -> 2990 | D10: =SUM(F10:W10) -> 5382000 | F10: ='Закупки и склад'!F$25*$C10 -> 0 | G10: ='Закупки и склад'!G$25*$C10 -> 0 | H10: ='Закупки и склад'!H$25*$C10 -> 107640 | I10: ='Закупки и склад'!I$25*$C10 -> 179400 | J10: ='Закупки и склад'!J$25*$C10 -> 251160 | K10: ='Закупки и склад'!K$25*$C10 -> 304980 | L10: ='Закупки и склад'!L$25*$C10 -> 358800 | M10: ='Закупки и склад'!M$25*$C10 -> 358800 | ... W10: ='Закупки и склад'!W$25*$C10 -> 376740
A11: =""&Допущения!$E$38 -> Держатель телефона MagSafe | B11: ₽ | C11: ='Юнит-экономика'!$E$6 -> 1290 | D11: =SUM(F11:W11) -> 5031000 | F11: ='Закупки и склад'!F$26*$C11 -> 0 | G11: ='Закупки и склад'!G$26*$C11 -> 0 | H11: ='Закупки и склад'!H$26*$C11 -> 100620 | I11: ='Закупки и склад'!I$26*$C11 -> 167700 | J11: ='Закупки и склад'!J$26*$C11 -> 234780 | K11: ='Закупки и склад'!K$26*$C11 -> 285090 | L11: ='Закупки и склад'!L$26*$C11 -> 335400 | M11: ='Закупки и склад'!M$26*$C11 -> 335400 | ... W11: ='Закупки и склад'!W$26*$C11 -> 352170
A12: =""&Допущения!$F$38 -> Чехлы на сиденья, комплект | B12: ₽ | C12: ='Юнит-экономика'!$F$6 -> 4490 | D12: =SUM(F12:W12) -> 4041000 | F12: ='Закупки и склад'!F$27*$C12 -> 0 | G12: ='Закупки и склад'!G$27*$C12 -> 0 | H12: ='Закупки и склад'!H$27*$C12 -> 80820 | I12: ='Закупки и склад'!I$27*$C12 -> 134700 | J12: ='Закупки и склад'!J$27*$C12 -> 188580 | K12: ='Закупки и склад'!K$27*$C12 -> 228990 | L12: ='Закупки и склад'!L$27*$C12 -> 269400 | M12: ='Закупки и склад'!M$27*$C12 -> 269400 | ... W12: ='Закупки и склад'!W$27*$C12 -> 282870
A13: =""&Допущения!$G$38 -> Видеорегистратор Wi-Fi | B13: ₽ | C13: ='Юнит-экономика'!$G$6 -> 3490 | D13: =SUM(F13:W13) -> 4721970 | F13: ='Закупки и склад'!F$28*$C13 -> 0 | G13: ='Закупки и склад'!G$28*$C13 -> 0 | H13: ='Закупки и склад'!H$28*$C13 -> 94230 | I13: ='Закупки и склад'!I$28*$C13 -> 157050 | J13: ='Закупки и склад'!J$28*$C13 -> 219870 | K13: ='Закупки и склад'!K$28*$C13 -> 268730 | L13: ='Закупки и склад'!L$28*$C13 -> 314100 | M13: ='Закупки и склад'!M$28*$C13 -> 314100 | ... W13: ='Закупки и склад'!W$28*$C13 -> 331550
A14: Себестоимость продаж | B14: ₽ | D14: =SUM(F14:W14) -> 11117545 | F14: =SUM(F15:F19) -> 0 | G14: =SUM(G15:G19) -> 0 | H14: =SUM(H15:H19) -> 222248.27 | I14: =SUM(I15:I19) -> 370413.78 | J14: =SUM(J15:J19) -> 518579.3 | K14: =SUM(K15:K19) -> 630558.7 | L14: =SUM(L15:L19) -> 740827.57 | M14: =SUM(M15:M19) -> 740827.57 | ... W14: =SUM(W15:W19) -> 778724.21
A15: =""&Допущения!$C$38 -> Органайзер в багажник | B15: ₽ | C15: ='Юнит-экономика'!$C$20 -> 1026.7768 | D15: =SUM(F15:W15) -> 2156231.3 | F15: ='Закупки и склад'!F$24*$C15 -> 0 | G15: ='Закупки и склад'!G$24*$C15 -> 0 | H15: ='Закупки и склад'!H$24*$C15 -> 43124.626 | I15: ='Закупки и склад'!I$24*$C15 -> 71874.376 | J15: ='Закупки и склад'!J$24*$C15 -> 100624.13 | K15: ='Закупки и склад'!K$24*$C15 -> 122186.44 | L15: ='Закупки и склад'!L$24*$C15 -> 143748.75 | M15: ='Закупки и склад'!M$24*$C15 -> 143748.75 | ... W15: ='Закупки и склад'!W$24*$C15 -> 150936.19
A16: =""&Допущения!$D$38 -> Автопылесос беспроводной | B16: ₽ | C16: ='Юнит-экономика'!$D$20 -> 1313.3625 | D16: =SUM(F16:W16) -> 2364052.6 | F16: ='Закупки и склад'!F$25*$C16 -> 0 | G16: ='Закупки и склад'!G$25*$C16 -> 0 | H16: ='Закупки и склад'!H$25*$C16 -> 47281.051 | I16: ='Закупки и склад'!I$25*$C16 -> 78801.752 | J16: ='Закупки и склад'!J$25*$C16 -> 110322.45 | K16: ='Закупки и склад'!K$25*$C16 -> 133962.98 | L16: ='Закупки и склад'!L$25*$C16 -> 157603.5 | M16: ='Закупки и склад'!M$25*$C16 -> 157603.5 | ... W16: ='Закупки и склад'!W$25*$C16 -> 165483.68
A17: =""&Допущения!$E$38 -> Держатель телефона MagSafe | B17: ₽ | C17: ='Юнит-экономика'!$E$20 -> 473.76547 | D17: =SUM(F17:W17) -> 1847685.3 | F17: ='Закупки и склад'!F$26*$C17 -> 0 | G17: ='Закупки и склад'!G$26*$C17 -> 0 | H17: ='Закупки и склад'!H$26*$C17 -> 36953.706 | I17: ='Закупки и склад'!I$26*$C17 -> 61589.511 | J17: ='Закупки и склад'!J$26*$C17 -> 86225.315 | K17: ='Закупки и склад'!K$26*$C17 -> 104702.17 | L17: ='Закупки и склад'!L$26*$C17 -> 123179.02 | M17: ='Закупки и склад'!M$26*$C17 -> 123179.02 | ... W17: ='Закупки и склад'!W$26*$C17 -> 129337.97
A18: =""&Допущения!$F$38 -> Чехлы на сиденья, комплект | B18: ₽ | C18: ='Юнит-экономика'!$F$20 -> 2705.811 | D18: =SUM(F18:W18) -> 2435229.9 | F18: ='Закупки и склад'!F$27*$C18 -> 0 | G18: ='Закупки и склад'!G$27*$C18 -> 0 | H18: ='Закупки и склад'!H$27*$C18 -> 48704.598 | I18: ='Закупки и склад'!I$27*$C18 -> 81174.33 | J18: ='Закупки и склад'!J$27*$C18 -> 113644.06 | K18: ='Закупки и склад'!K$27*$C18 -> 137996.36 | L18: ='Закупки и склад'!L$27*$C18 -> 162348.66 | M18: ='Закупки и склад'!M$27*$C18 -> 162348.66 | ... W18: ='Закупки и склад'!W$27*$C18 -> 170466.09
A19: =""&Допущения!$G$38 -> Видеорегистратор Wi-Fi | B19: ₽ | C19: ='Юнит-экономика'!$G$20 -> 1710.5292 | D19: =SUM(F19:W19) -> 2314346 | F19: ='Закупки и склад'!F$28*$C19 -> 0 | G19: ='Закупки и склад'!G$28*$C19 -> 0 | H19: ='Закупки и склад'!H$28*$C19 -> 46184.288 | I19: ='Закупки и склад'!I$28*$C19 -> 76973.814 | J19: ='Закупки и склад'!J$28*$C19 -> 107763.34 | K19: ='Закупки и склад'!K$28*$C19 -> 131710.75 | L19: ='Закупки и склад'!L$28*$C19 -> 153947.63 | M19: ='Закупки и склад'!M$28*$C19 -> 153947.63 | ... W19: ='Закупки и склад'!W$28*$C19 -> 162500.27
A20: Валовая прибыль | B20: ₽ | D20: =SUM(F20:W20) -> 13287425 | F20: =F8-F14 -> 0 | G20: =G8-G14 -> 0 | H20: =H8-H14 -> 265641.73 | I20: =I8-I14 -> 442736.22 | J20: =J8-J14 -> 619830.7 | K20: =K8-K14 -> 753541.3 | L20: =L8-L14 -> 885472.43 | M20: =M8-M14 -> 885472.43 | ... W20: =W8-W14 -> 930635.79
A21: Валовая маржа | B21: % | D21: =IFERROR(D20/D8,0) -> 0.5444557 | F21: =IFERROR(F20/F8,0) -> 0 | G21: =IFERROR(G20/G8,0) -> 0 | H21: =IFERROR(H20/H8,0) -> 0.54447054 | I21: =IFERROR(I20/I8,0) -> 0.54447054 | J21: =IFERROR(J20/J8,0) -> 0.54447054 | K21: =IFERROR(K20/K8,0) -> 0.54442692 | L21: =IFERROR(L20/L8,0) -> 0.54447054 | M21: =IFERROR(M20/M8,0) -> 0.54447054 | ... W21: =IFERROR(W20/W8,0) -> 0.54443522
A23: Комиссия маркетплейса | B23: ₽ | D23: =SUM(F23:W23) -> 4631694.9 | F23: =SUM(F24:F28) -> 0 | G23: =SUM(G24:G28) -> 0 | H23: =SUM(H24:H28) -> 92598.3 | I23: =SUM(I24:I28) -> 154330.5 | J23: =SUM(J24:J28) -> 216062.7 | K23: =SUM(K24:K28) -> 262658.5 | L23: =SUM(L24:L28) -> 308661 | M23: =SUM(M24:M28) -> 308661 | ... W23: =SUM(W24:W28) -> 324390.7
A24: =""&Допущения!$C$38 -> Органайзер в багажник | B24: ₽ | C24: =Допущения!$C$50 -> 0.2 | D24: =SUM(F24:W24) -> 1045800 | F24: =F9*$C24 -> 0 | G24: =G9*$C24 -> 0 | H24: =H9*$C24 -> 20916 | I24: =I9*$C24 -> 34860 | J24: =J9*$C24 -> 48804 | K24: =K9*$C24 -> 59262 | L24: =L9*$C24 -> 69720 | M24: =M9*$C24 -> 69720 | ... W24: =W9*$C24 -> 73206
A25: =""&Допущения!$D$38 -> Автопылесос беспроводной | B25: ₽ | C25: =Допущения!$D$50 -> 0.18 | D25: =SUM(F25:W25) -> 968760 | F25: =F10*$C25 -> 0 | G25: =G10*$C25 -> 0 | H25: =H10*$C25 -> 19375.2 | I25: =I10*$C25 -> 32292 | J25: =J10*$C25 -> 45208.8 | K25: =K10*$C25 -> 54896.4 | L25: =L10*$C25 -> 64584 | M25: =M10*$C25 -> 64584 | ... W25: =W10*$C25 -> 67813.2
A26: =""&Допущения!$E$38 -> Держатель телефона MagSafe | B26: ₽ | C26: =Допущения!$E$50 -> 0.2 | D26: =SUM(F26:W26) -> 1006200 | F26: =F11*$C26 -> 0 | G26: =G11*$C26 -> 0 | H26: =H11*$C26 -> 20124 | I26: =I11*$C26 -> 33540 | J26: =J11*$C26 -> 46956 | K26: =K11*$C26 -> 57018 | L26: =L11*$C26 -> 67080 | M26: =M11*$C26 -> 67080 | ... W26: =W11*$C26 -> 70434
A27: =""&Допущения!$F$38 -> Чехлы на сиденья, комплект | B27: ₽ | C27: =Допущения!$F$50 -> 0.2 | D27: =SUM(F27:W27) -> 808200 | F27: =F12*$C27 -> 0 | G27: =G12*$C27 -> 0 | H27: =H12*$C27 -> 16164 | I27: =I12*$C27 -> 26940 | J27: =J12*$C27 -> 37716 | K27: =K12*$C27 -> 45798 | L27: =L12*$C27 -> 53880 | M27: =M12*$C27 -> 53880 | ... W27: =W12*$C27 -> 56574
A28: =""&Допущения!$G$38 -> Видеорегистратор Wi-Fi | B28: ₽ | C28: =Допущения!$G$50 -> 0.17 | D28: =SUM(F28:W28) -> 802734.9 | F28: =F13*$C28 -> 0 | G28: =G13*$C28 -> 0 | H28: =H13*$C28 -> 16019.1 | I28: =I13*$C28 -> 26698.5 | J28: =J13*$C28 -> 37377.9 | K28: =K13*$C28 -> 45684.1 | L28: =L13*$C28 -> 53397 | M28: =M13*$C28 -> 53397 | ... W28: =W13*$C28 -> 56363.5
A29: Логистика маркетплейса (с возвратами) | B29: ₽ | D29: =SUM(F29:W29) -> 1051458.8 | F29: =SUM(F30:F34) -> 0 | G29: =SUM(G30:G34) -> 0 | H29: =SUM(H30:H34) -> 21023.604 | I29: =SUM(I30:I34) -> 35039.34 | J29: =SUM(J30:J34) -> 49055.076 | K29: =SUM(K30:K34) -> 59613.307 | L29: =SUM(L30:L34) -> 70078.68 | M29: =SUM(M30:M34) -> 70078.68 | ... W29: =SUM(W30:W34) -> 73629.043
A30: =""&Допущения!$C$38 -> Органайзер в багажник | B30: ₽ | C30: ='Юнит-экономика'!$C$25 -> 118.42105 | D30: =SUM(F30:W30) -> 248684.21 | F30: ='Закупки и склад'!F$24*$C30 -> 0 | G30: ='Закупки и склад'!G$24*$C30 -> 0 | H30: ='Закупки и склад'!H$24*$C30 -> 4973.6842 | I30: ='Закупки и склад'!I$24*$C30 -> 8289.4737 | J30: ='Закупки и склад'!J$24*$C30 -> 11605.263 | K30: ='Закупки и склад'!K$24*$C30 -> 14092.105 | L30: ='Закупки и склад'!L$24*$C30 -> 16578.947 | M30: ='Закупки и склад'!M$24*$C30 -> 16578.947 | ... W30: ='Закупки и склад'!W$24*$C30 -> 17407.895
A31: =""&Допущения!$D$38 -> Автопылесос беспроводной | B31: ₽ | C31: ='Юнит-экономика'!$D$25 -> 102.17391 | D31: =SUM(F31:W31) -> 183913.04 | F31: ='Закупки и склад'!F$25*$C31 -> 0 | G31: ='Закупки и склад'!G$25*$C31 -> 0 | H31: ='Закупки и склад'!H$25*$C31 -> 3678.2609 | I31: ='Закупки и склад'!I$25*$C31 -> 6130.4348 | J31: ='Закупки и склад'!J$25*$C31 -> 8582.6087 | K31: ='Закупки и склад'!K$25*$C31 -> 10421.739 | L31: ='Закупки и склад'!L$25*$C31 -> 12260.87 | M31: ='Закупки и склад'!M$25*$C31 -> 12260.87 | ... W31: ='Закупки и склад'!W$25*$C31 -> 12873.913
A32: =""&Допущения!$E$38 -> Держатель телефона MagSafe | B32: ₽ | C32: ='Юнит-экономика'!$E$25 -> 79.032258 | D32: =SUM(F32:W32) -> 308225.81 | F32: ='Закупки и склад'!F$26*$C32 -> 0 | G32: ='Закупки и склад'!G$26*$C32 -> 0 | H32: ='Закупки и склад'!H$26*$C32 -> 6164.5161 | I32: ='Закупки и склад'!I$26*$C32 -> 10274.194 | J32: ='Закупки и склад'!J$26*$C32 -> 14383.871 | K32: ='Закупки и склад'!K$26*$C32 -> 17466.129 | L32: ='Закупки и склад'!L$26*$C32 -> 20548.387 | M32: ='Закупки и склад'!M$26*$C32 -> 20548.387 | ... W32: ='Закупки и склад'!W$26*$C32 -> 21575.806
A33: =""&Допущения!$F$38 -> Чехлы на сиденья, комплект | B33: ₽ | C33: ='Юнит-экономика'!$F$25 -> 205.55556 | D33: =SUM(F33:W33) -> 185000 | F33: ='Закупки и склад'!F$27*$C33 -> 0 | G33: ='Закупки и склад'!G$27*$C33 -> 0 | H33: ='Закупки и склад'!H$27*$C33 -> 3700 | I33: ='Закупки и склад'!I$27*$C33 -> 6166.6667 | J33: ='Закупки и склад'!J$27*$C33 -> 8633.3333 | K33: ='Закупки и склад'!K$27*$C33 -> 10483.333 | L33: ='Закупки и склад'!L$27*$C33 -> 12333.333 | M33: ='Закупки и склад'!M$27*$C33 -> 12333.333 | ... W33: ='Закупки и склад'!W$27*$C33 -> 12950
A34: =""&Допущения!$G$38 -> Видеорегистратор Wi-Fi | B34: ₽ | C34: ='Юнит-экономика'!$G$25 -> 92.857143 | D34: =SUM(F34:W34) -> 125635.71 | F34: ='Закупки и склад'!F$28*$C34 -> 0 | G34: ='Закупки и склад'!G$28*$C34 -> 0 | H34: ='Закупки и склад'!H$28*$C34 -> 2507.1429 | I34: ='Закупки и склад'!I$28*$C34 -> 4178.5714 | J34: ='Закупки и склад'!J$28*$C34 -> 5850 | K34: ='Закупки и склад'!K$28*$C34 -> 7150 | L34: ='Закупки и склад'!L$28*$C34 -> 8357.1429 | M34: ='Закупки и склад'!M$28*$C34 -> 8357.1429 | ... W34: ='Закупки и склад'!W$28*$C34 -> 8821.4286
A35: Реклама | B35: ₽ | C35: =ДРР -> 0.08 | D35: =SUM(F35:W35) -> 1952397.6 | F35: =F8*$C35 -> 0 | G35: =G8*$C35 -> 0 | H35: =H8*$C35 -> 39031.2 | I35: =I8*$C35 -> 65052 | J35: =J8*$C35 -> 91072.8 | K35: =K8*$C35 -> 110728 | L35: =L8*$C35 -> 130104 | M35: =M8*$C35 -> 130104 | ... W35: =W8*$C35 -> 136748.8
A36: Постоянные расходы | B36: ₽ | C36: =Пост_расходы -> 50000 | D36: =SUM(F36:W36) -> 900000 | F36: =$C36 -> 50000 | G36: =$C36 -> 50000 | H36: =$C36 -> 50000 | I36: =$C36 -> 50000 | J36: =$C36 -> 50000 | K36: =$C36 -> 50000 | L36: =$C36 -> 50000 | M36: =$C36 -> 50000 | ... W36: =$C36 -> 50000
A37: Стартовые расходы | B37: ₽ | C37: =Старт_расходы -> 60000 | D37: =SUM(F37:W37) -> 60000 | F37: =IF(F$4=1,$C37,0) -> 60000 | G37: =IF(G$4=1,$C37,0) -> 0 | H37: =IF(H$4=1,$C37,0) -> 0 | I37: =IF(I$4=1,$C37,0) -> 0 | J37: =IF(J$4=1,$C37,0) -> 0 | K37: =IF(K$4=1,$C37,0) -> 0 | L37: =IF(L$4=1,$C37,0) -> 0 | M37: =IF(M$4=1,$C37,0) -> 0 | ... W37: =IF(W$4=1,$C37,0) -> 0
A38: Сертификация | B38: ₽ | D38: =SUM(F38:W38) -> 175000 | F38: ='Денежный поток'!F$52 -> 175000 | G38: ='Денежный поток'!G$52 -> 0 | H38: ='Денежный поток'!H$52 -> 0 | I38: ='Денежный поток'!I$52 -> 0 | J38: ='Денежный поток'!J$52 -> 0 | K38: ='Денежный поток'!K$52 -> 0 | L38: ='Денежный поток'!L$52 -> 0 | M38: ='Денежный поток'!M$52 -> 0 | ... W38: ='Денежный поток'!W$52 -> 0
A39: Прибыль до налога | B39: ₽ | D39: =SUM(F39:W39) -> 4516873.7 | F39: =F20-F23-F29-F35-F36-F37-F38 -> -285000 | G39: =G20-G23-G29-G35-G36-G37-G38 -> -50000 | H39: =H20-H23-H29-H35-H36-H37-H38 -> 62988.626 | I39: =I20-I23-I29-I35-I36-I37-I38 -> 138314.38 | J39: =J20-J23-J29-J35-J36-J37-J38 -> 213640.13 | K39: =K20-K23-K29-K35-K36-K37-K38 -> 270541.5 | L39: =L20-L23-L29-L35-L36-L37-L38 -> 326628.75 | M39: =M20-M23-M29-M35-M36-M37-M38 -> 326628.75 | ... W39: =W20-W23-W29-W35-W36-W37-W38 -> 345867.25
A41: Доходы с начала года (служебная) | B41: ₽ | F41: =SUMIFS($F8:$W8,$F$6:$W$6,F$6,$F$4:$W$4,"<="&F$4) -> 0 | G41: =SUMIFS($F8:$W8,$F$6:$W$6,G$6,$F$4:$W$4,"<="&G$4) -> 0 | H41: =SUMIFS($F8:$W8,$F$6:$W$6,H$6,$F$4:$W$4,"<="&H$4) -> 487890 | I41: =SUMIFS($F8:$W8,$F$6:$W$6,I$6,$F$4:$W$4,"<="&I$4) -> 1301040 | J41: =SUMIFS($F8:$W8,$F$6:$W$6,J$6,$F$4:$W$4,"<="&J$4) -> 2439450 | K41: =SUMIFS($F8:$W8,$F$6:$W$6,K$6,$F$4:$W$4,"<="&K$4) -> 3823550 | L41: =SUMIFS($F8:$W8,$F$6:$W$6,L$6,$F$4:$W$4,"<="&L$4) -> 5449850 | M41: =SUMIFS($F8:$W8,$F$6:$W$6,M$6,$F$4:$W$4,"<="&M$4) -> 7076150 | ... W41: =SUMIFS($F8:$W8,$F$6:$W$6,W$6,$F$4:$W$4,"<="&W$4) -> 6508690
A42: Прибыль до налога с начала года (служебная) | B42: ₽ | F42: =SUMIFS($F39:$W39,$F$6:$W$6,F$6,$F$4:$W$4,"<="&F$4) -> -285000 | G42: =SUMIFS($F39:$W39,$F$6:$W$6,G$6,$F$4:$W$4,"<="&G$4) -> -335000 | H42: =SUMIFS($F39:$W39,$F$6:$W$6,H$6,$F$4:$W$4,"<="&H$4) -> 62988.626 | I42: =SUMIFS($F39:$W39,$F$6:$W$6,I$6,$F$4:$W$4,"<="&I$4) -> 201303 | J42: =SUMIFS($F39:$W39,$F$6:$W$6,J$6,$F$4:$W$4,"<="&J$4) -> 414943.13 | K42: =SUMIFS($F39:$W39,$F$6:$W$6,K$6,$F$4:$W$4,"<="&K$4) -> 685484.63 | L42: =SUMIFS($F39:$W39,$F$6:$W$6,L$6,$F$4:$W$4,"<="&L$4) -> 1012113.4 | M42: =SUMIFS($F39:$W39,$F$6:$W$6,M$6,$F$4:$W$4,"<="&M$4) -> 1338742.1 | ... W42: =SUMIFS($F39:$W39,$F$6:$W$6,W$6,$F$4:$W$4,"<="&W$4) -> 1307329.1
A43: Налог с начала года (служебная) | B43: ₽ | F43: =CHOOSE(Налог_номер,Ставка_УСН6*F41,MAX(Ставка_УСН15*F42,Мин_налог_УСН15*F41),Ставка_НПД*F41) -> 0 | G43: =CHOOSE(Налог_номер,Ставка_УСН6*G41,MAX(Ставка_УСН15*G42,Мин_налог_УСН15*G41),Ставка_НПД*G41) -> 0 | H43: =CHOOSE(Налог_номер,Ставка_УСН6*H41,MAX(Ставка_УСН15*H42,Мин_налог_УСН15*H41),Ставка_НПД*H41) -> 29273.4 | I43: =CHOOSE(Налог_номер,Ставка_УСН6*I41,MAX(Ставка_УСН15*I42,Мин_налог_УСН15*I41),Ставка_НПД*I41) -> 78062.4 | J43: =CHOOSE(Налог_номер,Ставка_УСН6*J41,MAX(Ставка_УСН15*J42,Мин_налог_УСН15*J41),Ставка_НПД*J41) -> 146367 | K43: =CHOOSE(Налог_номер,Ставка_УСН6*K41,MAX(Ставка_УСН15*K42,Мин_налог_УСН15*K41),Ставка_НПД*K41) -> 229413 | L43: =CHOOSE(Налог_номер,Ставка_УСН6*L41,MAX(Ставка_УСН15*L42,Мин_налог_УСН15*L41),Ставка_НПД*L41) -> 326991 | M43: =CHOOSE(Налог_номер,Ставка_УСН6*M41,MAX(Ставка_УСН15*M42,Мин_налог_УСН15*M41),Ставка_НПД*M41) -> 424569 | ... W43: =CHOOSE(Налог_номер,Ставка_УСН6*W41,MAX(Ставка_УСН15*W42,Мин_налог_УСН15*W41),Ставка_НПД*W41) -> 390521.4
A45: Налог (начислен за месяц) | B45: ₽ | D45: =SUM(F45:W45) -> 1464298.2 | F45: =F43-IF(E$6=F$6,E43,0) -> 0 | G45: =G43-IF(F$6=G$6,F43,0) -> 0 | H45: =H43-IF(G$6=H$6,G43,0) -> 29273.4 | I45: =I43-IF(H$6=I$6,H43,0) -> 48789 | J45: =J43-IF(I$6=J$6,I43,0) -> 68304.6 | K45: =K43-IF(J$6=K$6,J43,0) -> 83046 | L45: =L43-IF(K$6=L$6,K43,0) -> 97578 | M45: =M43-IF(L$6=M$6,L43,0) -> 97578 | ... W45: =W43-IF(V$6=W$6,V43,0) -> 102561.6
A46: Чистая прибыль | B46: ₽ | D46: =SUM(F46:W46) -> 3052575.5 | F46: =F39-F45 -> -285000 | G46: =G39-G45 -> -50000 | H46: =H39-H45 -> 33715.226 | I46: =I39-I45 -> 89525.377 | J46: =J39-J45 -> 145335.53 | K46: =K39-K45 -> 187495.5 | L46: =L39-L45 -> 229050.75 | M46: =M39-M45 -> 229050.75 | ... W46: =W39-W45 -> 243305.65
A47: Чистая прибыль нарастающим итогом | B47: ₽ | F47: =E47+F46 -> -285000 | G47: =F47+G46 -> -335000 | H47: =G47+H46 -> -301284.77 | I47: =H47+I46 -> -211759.4 | J47: =I47+J46 -> -66423.868 | K47: =J47+K46 -> 121071.63 | L47: =K47+L46 -> 350122.38 | M47: =L47+M46 -> 579173.14 | ... W47: =V47+W46 -> 3052575.5
A48: Рентабельность по чистой прибыли | B48: % | D48: =IFERROR(D46/D8,0) -> 0.12508007 | F48: =IFERROR(F46/F8,0) -> 0 | G48: =IFERROR(G46/G8,0) -> 0 | H48: =IFERROR(H46/H8,0) -> 0.069104155 | I48: =IFERROR(I46/I8,0) -> 0.110097 | J48: =IFERROR(J46/J8,0) -> 0.12766536 | K48: =IFERROR(K46/K8,0) -> 0.13546384 | L48: =IFERROR(L46/L8,0) -> 0.14084164 | M48: =IFERROR(M46/M8,0) -> 0.14084164 | ... W48: =IFERROR(W46/W8,0) -> 0.14233728
A51: Выручка по календарным годам (для проверки лимитов НПД и порога НДС)
A52: Выручка за календарный год | B52: год | C52: =YEAR(Дата_начала)+0 -> 2026 | D52: =SUMIFS($F$8:$W$8,$F$6:$W$6,$C52) -> 0
A53: Выручка за календарный год | B53: год | C53: =YEAR(Дата_начала)+1 -> 2027 | D53: =SUMIFS($F$8:$W$8,$F$6:$W$6,$C53) -> 17896280
A54: Выручка за календарный год | B54: год | C54: =YEAR(Дата_начала)+2 -> 2028 | D54: =SUMIFS($F$8:$W$8,$F$6:$W$6,$C54) -> 6508690
A55: Максимум за календарный год | D55: =MAX(D52:D54) -> 17896280

Sheet Чувствительность
A1: Чувствительность: как меняется результат от курса, цены и объёма
A2: Таблицы данных Excel пересчитывают всю модель для каждой клетки (от активного сценария; курс в таблице заменяет курс сценария). Оси — жёлтые, их можно менять. Если включён режим «Автоматически, кроме таблиц данных» — нажмите F9.
A3: ДЕМО-ДАННЫЕ: все цифры — пример. Ставки пошлин, НДС, налогов и тарифы маркетплейса уточните под свой товар.
B5: Служебные ячейки анализа (не менять, должны быть 0)
B6: Курс для анализа, ₽/¥ (0 = курс сценария) | C6: 0
B7: Изменение цены для анализа | C7: 0
B8: Изменение объёма продаж для анализа | C8: 0
B10: 1. Чистая прибыль за 18 мес, ₽: курс юаня × изменение цены продажи
B11: Курс ↓ / цена → | C11: =ЧП_итого -> 3052575.5 | D11: -0.15 | E11: -0.1 | F11: -0.05 | G11: 0 | H11: 0.05 | I11: 0.1 | J11: 0.15
B12: ₽ за ¥ | C12: 10 | D12: 1877486 | E12: 2695315 | F12: 3513144 | G12: 4330972.9 | H12: 5148801.9 | I12: 5966630.9 | J12: 6784459.8
C13: 11 | D13: 1238287.3 | E13: 2056116.3 | F13: 2873945.2 | G13: 3691774.2 | H13: 4509603.2 | I13: 5327432.1 | J13: 6145261.1
C14: 12 | D14: 599088.56 | E14: 1416917.5 | F14: 2234746.5 | G14: 3052575.5 | H14: 3870404.4 | I14: 4688233.4 | J14: 5506062.4
C15: 13 | D15: -40110.17 | E15: 777718.8 | F15: 1595547.8 | G15: 2413376.7 | H15: 3231205.7 | I15: 4049034.7 | J15: 4866863.6
C16: 14 | D16: -679308.9 | E16: 138520.06 | F16: 956349.03 | G16: 1774178 | H16: 2592007 | I16: 3409835.9 | J16: 4227664.9
C17: 15 | D17: -1318507.6 | E17: -500678.67 | F17: 317150.3 | G17: 1134979.3 | H17: 1952808.2 | I17: 2770637.2 | J17: 3588466.2
C18: 16 | D18: -1957706.4 | E18: -1139877.4 | F18: -322048.44 | G18: 495780.53 | H18: 1313609.5 | I18: 2131438.5 | J18: 2949267.4
B21: 2. Чистая прибыль за 18 мес, ₽: курс юаня × изменение объёма продаж
B22: Курс ↓ / объём → | C22: =ЧП_итого -> 3052575.5 | D22: -0.3 | E22: -0.2 | F22: -0.1 | G22: 0 | H22: 0.1 | I22: 0.2 | J22: 0.3
B23: ₽ за ¥ | C23: 10 | D23: 2690169.2 | E23: 3237245.3 | F23: 3781999.4 | G23: 4330972.9 | H23: 4876967.4 | I23: 5419584 | J23: 5968797.6
C24: 11 | D24: 2242769.9 | E24: 2726112.2 | F24: 3206958.8 | G24: 3691774.2 | H24: 4174012.7 | I24: 4653063.8 | J24: 5138201.6
C25: 12 | D25: 1795370.6 | E25: 2214979 | F25: 2631918.2 | G25: 3052575.5 | H25: 3471058 | I25: 3886543.6 | J25: 4307605.6
C26: 13 | D26: 1347971.3 | E26: 1703845.8 | F26: 2056877.5 | G26: 2413376.7 | H26: 2768103.3 | I26: 3120023.4 | J26: 3477009.5
C27: 14 | D27: 900572.04 | E27: 1192712.6 | F27: 1481836.9 | G27: 1774178 | H27: 2065148.6 | I27: 2353503.2 | J27: 2646413.5
C28: 15 | D28: 453172.75 | E28: 681579.47 | F28: 906796.33 | G28: 1134979.3 | H28: 1362193.9 | I28: 1586983 | J28: 1815817.5
C29: 16 | D29: 5773.4669 | E29: 170446.29 | F29: 331755.72 | G29: 495780.53 | H29: 659239.21 | I29: 820462.82 | J29: 985221.46
B32: 3. Потребность в деньгах (пик вложений), ₽: курс юаня × изменение объёма
B33: Курс ↓ / объём → | C33: =Пик_вложений -> 2397876.7 | D33: -0.3 | E33: -0.2 | F33: -0.1 | G33: 0 | H33: 0.1 | I33: 0.2 | J33: 0.3
B34: ₽ за ¥ | C34: 10 | D34: 1604078.3 | E34: 1829623.1 | F34: 1793793.8 | G34: 1991284.3 | H34: 2015067.4 | I34: 2162887.9 | J34: 2169062.3
C35: 11 | D35: 1780223.3 | E35: 2002160.2 | F35: 1975426.3 | G35: 2158346.8 | H35: 2279885.6 | I35: 2344520.4 | J35: 2424683.7
C36: 12 | D36: 1956368.4 | E36: 2174697.3 | F36: 2167481.7 | G36: 2397876.7 | H36: 2544703.7 | I36: 2544269 | J36: 2724453.4
C37: 13 | D37: 2132513.5 | E37: 2347234.4 | F37: 2381191.9 | G37: 2637406.6 | H37: 2809521.9 | I37: 2820627.3 | J37: 3024223.1
C38: 14 | D38: 2308658.6 | E38: 2561855.1 | F38: 2594902.2 | G38: 2876936.5 | H38: 3074340 | I38: 3096985.6 | J38: 3323992.8
C39: 15 | D39: 2541401.8 | E39: 2802837 | F39: 2808612.4 | G39: 3116466.4 | H39: 3339158.2 | I39: 3435294.4 | J39: 3623762.6
C40: 16 | D40: 2892933.3 | E40: 3070768.7 | F40: 3210204.2 | G40: 3355996.3 | H40: 3603976.3 | I40: 3885531.2 | J40: 3923532.3
